LAB 6/Q1/question1.v
module question1(W, E, Y);

input [2:0] W;
input E;
output [0:7] Y;

wire [0:7] Y1, Y2;

dec2to4 d1(W, E, Y1);
dec2to4 d2(W, ~E, Y2);

assign Y = Y1 | Y2;

endmodule


module dec2to4(W, E, Y);
input [2:0] W;
input E;
output reg [0:7] Y;
integer k;

always @(*) begin
for (k = 0; k <= 3; k = k + 1) begin
if (E) begin
Y[k]   = (W[1:0] == k);
Y[k+4] = 1'b0;
end else begin
Y[k]   = 1'b0;
Y[k+4] = (W[1:0] == k);
end
end
end
endmodule

LAB 6/Q1/question1_tb.v
`include "question1.v"
`timescale 1ns/1ns

module question1_tb();
reg [2:0]W;
reg E;
wire [0:7] Y;

integer i,j;
question1 q1(W, E, Y);
initial
begin
	$dumpfile("question1.vcd");
	$dumpvars(0, question1_tb);
	for(i=0;i<=1;i=i+1) begin
		for(j=0;j<=7;j=j+1) begin
			W=j;E=i;
			#20;
		end
	end
	$display("Test Complete");
end
endmodule

LAB 6/Q1/question1.vcd
$date
	Wed Sep  2 09:50:40 2026
$end
$version
	Icarus Verilog
$end
$timescale
	1ns
$end
$scope module question1_tb $end
$var wire 8 ! Y [0:7] $end
$var reg 1 " E $end
$var reg 3 # W [2:0] $end
$var integer 32 $ i [31:0] $end
$var integer 32 % j [31:0] $end
$scope module q1 $end
$var wire 1 " E $end
$var wire 3 & W [2:0] $end
$var wire 8 ' Y [0:7] $end
$var wire 8 ( Y2 [0:7] $end
$var wire 8 ) Y1 [0:7] $end
$scope module d1 $end
$var wire 1 " E $end
$var wire 3 * W [2:0] $end
$var reg 8 + Y [0:7] $end
$var integer 32 , k [31:0] $end
$upscope $end
$scope module d2 $end
$var wire 1 - E $end
$var wire 3 . W [2:0] $end
$var reg 8 / Y [0:7] $end
$var integer 32 0 k [31:0] $end
$upscope $end
$upscope $end
$upscope $end
$enddefinitions $end
#0
$dumpvars
b100 0
b10000000 /
b0 .
1-
b100 ,
b1000 +
b0 *
b1000 )
b10000000 (
b10001000 '
b0 &
b0 %
b0 $
b0 #
0"
b10001000 !
$end
#20
b1000100 !
b1000100 '
b100 )
b100 +
b100 ,
b1000000 (
b1000000 /
b100 0
b1 #
b1 &
b1 *
b1 .
b1 %
#40
b100010 !
b100010 '
b10 )
b10 +
b100 ,
b100000 (
b100000 /
b100 0
b10 #
b10 &
b10 *
b10 .
b10 %
#60
b10001 !
b10001 '
b1 )
b1 +
b100 ,
b10000 (
b10000 /
b100 0
b11 #
b11 &
b11 *
b11 .
b11 %
#80
b10001000 !
b10001000 '
b1000 )
b1000 +
b100 ,
b10000000 (
b10000000 /
b100 0
b100 #
b100 &
b100 *
b100 .
b100 %
#100
b1000100 !
b1000100 '
b100 )
b100 +
b100 ,
b1000000 (
b1000000 /
b100 0
b101 #
b101 &
b101 *
b101 .
b101 %
#120
b100010 !
b100010 '
b10 )
b10 +
b100 ,
b100000 (
b100000 /
b100 0
b110 #
b110 &
b110 *
b110 .
b110 %
#140
b10001 !
b10001 '
b1 )
b1 +
b100 ,
b10000 (
b10000 /
b100 0
b111 #
b111 &
b111 *
b111 .
b111 %
#160
b10001000 !
b10001000 '
0-
b10000000 )
b10000000 +
b100 ,
b1000 (
b1000 /
b100 0
1"
b0 #
b0 &
b0 *
b0 .
b1 $
b0 %
#180
b1000100 !
b1000100 '
b1000000 )
b1000000 +
b100 ,
b100 (
b100 /
b100 0
b1 #
b1 &
b1 *
b1 .
b1 %
#200
b100010 !
b100010 '
b100000 )
b100000 +
b100 ,
b10 (
b10 /
b100 0
b10 #
b10 &
b10 *
b10 .
b10 %
#220
b10001 !
b10001 '
b10000 )
b10000 +
b100 ,
b1 (
b1 /
b100 0
b11 #
b11 &
b11 *
b11 .
b11 %
#240
b10001000 !
b10001000 '
b10000000 )
b10000000 +
b100 ,
b1000 (
b1000 /
b100 0
b100 #
b100 &
b100 *
b100 .
b100 %
#260
b1000100 !
b1000100 '
b1000000 )
b1000000 +
b100 ,
b100 (
b100 /
b100 0
b101 #
b101 &
b101 *
b101 .
b101 %
#280
b100010 !
b100010 '
b100000 )
b100000 +
b100 ,
b10 (
b10 /
b100 0
b110 #
b110 &
b110 *
b110 .
b110 %
#300
b10001 !
b10001 '
b10000 )
b10000 +
b100 ,
b1 (
b1 /
b100 0
b111 #
b111 &
b111 *
b111 .
b111 %
#320
b10 $
b1000 %
