LAB 4/q4/question4.v
module adder_4bit(a, b, cin, sum, cout);
input [3:0] a, b;
input cin;
output [3:0] sum;
output cout;

assign {cout, sum} = a + b + cin;
endmodule


module question4(A, B, Cin, S, Cout);
input [3:0] A, B;
input Cin;
output [3:0] S;
output Cout;

wire [3:0] sum1;
wire cout1;
wire [3:0] correction;
wire needs_correction;


adder_4bit add1(A, B, Cin, sum1, cout1);
assign needs_correction = cout1 | (sum1[3] & (sum1[2] | sum1[1]));
assign Cout = needs_correction;
assign correction = {1'b0, needs_correction, needs_correction, 1'b0};
adder_4bit add2(sum1, correction, 1'b0, S, );

endmodule

LAB 4/q4/question4_tb.v
`timescale 1ns/1ns
`include "question4.v"

module question4_tb();
reg [3:0] A;
reg [3:0] B;
reg Cin;
wire [3:0] S;
wire Cout;

integer i, j, k;
question4 uut(A, B, Cin, S, Cout);

initial
begin
    $dumpfile("question4.vcd");
    $dumpvars(0, question4_tb);
    
    for (i = 0; i < 16; i = i + 1) begin
        for (j = 0; j < 16; j = j + 1) begin
            for (k = 0; k < 2; k = k + 1) begin
                A = i;
                B = j;
                Cin = k;
                #20;
            end
        end
    end
    $display("Test Complete!");
end
endmodule

LAB 4/q4/question4.vcd
$date
	Sat Aug 22 10:56:44 2026
$end
$version
	Icarus Verilog
$end
$timescale
	1ns
$end
$scope module question4_tb $end
$var wire 4 ! S [3:0] $end
$var wire 1 " Cout $end
$var reg 4 # A [3:0] $end
$var reg 4 $ B [3:0] $end
$var reg 1 % Cin $end
$var integer 32 & i [31:0] $end
$var integer 32 ' j [31:0] $end
$var integer 32 ( k [31:0] $end
$scope module uut $end
$var wire 4 ) A [3:0] $end
$var wire 4 * B [3:0] $end
$var wire 1 % Cin $end
$var wire 1 " Cout $end
$var wire 1 + needs_correction $end
$var wire 4 , sum1 [3:0] $end
$var wire 1 - cout1 $end
$var wire 4 . correction [3:0] $end
$var wire 4 / S [3:0] $end
$scope module add1 $end
$var wire 4 0 a [3:0] $end
$var wire 4 1 b [3:0] $end
$var wire 1 % cin $end
$var wire 4 2 sum [3:0] $end
$var wire 1 - cout $end
$upscope $end
$scope module add2 $end
$var wire 4 3 a [3:0] $end
$var wire 4 4 b [3:0] $end
$var wire 1 5 cin $end
$var wire 4 6 sum [3:0] $end
$var wire 1 7 cout $end
$upscope $end
$upscope $end
$upscope $end
$enddefinitions $end
#0
$dumpvars
07
b0 6
05
b0 4
b0 3
b0 2
b0 1
b0 0
b0 /
b0 .
0-
b0 ,
0+
b0 *
b0 )
b0 (
b0 '
b0 &
0%
b0 $
b0 #
0"
b0 !
$end
#20
b1 !
b1 /
b1 6
b1 ,
b1 2
b1 3
1%
b1 (
#40
0%
b1 $
b1 *
b1 1
b1 '
b0 (
#60
b10 !
b10 /
b10 6
b10 ,
b10 2
b10 3
1%
b1 (
#80
0%
b10 $
b10 *
b10 1
b10 '
b0 (
#100
b11 !
b11 /
b11 6
b11 ,
b11 2
b11 3
1%
b1 (
#120
0%
b11 $
b11 *
b11 1
b11 '
b0 (
#140
b100 !
b100 /
b100 6
b100 ,
b100 2
b100 3
1%
b1 (
#160
0%
b100 $
b100 *
b100 1
b100 '
b0 (
#180
b101 !
b101 /
b101 6
b101 ,
b101 2
b101 3
1%
b1 (
#200
0%
b101 $
b101 *
b101 1
b101 '
b0 (
#220
b110 !
b110 /
b110 6
b110 ,
b110 2
b110 3
1%
b1 (
#240
0%
b110 $
b110 *
b110 1
b110 '
b0 (
#260
b111 !
b111 /
b111 6
b111 ,
b111 2
b111 3
1%
b1 (
#280
0%
b111 $
b111 *
b111 1
b111 '
b0 (
#300
0"
b0 .
b0 4
0+
b1000 !
b1000 /
b1000 6
b1000 ,
b1000 2
b1000 3
1%
b1 (
#320
0%
b1000 $
b1000 *
b1000 1
b1000 '
b0 (
#340
b1001 !
b1001 /
b1001 6
b1001 ,
b1001 2
b1001 3
1%
b1 (
#360
0%
b1001 $
b1001 *
b1001 1
b1001 '
b0 (
#380
17
1"
b110 .
b110 4
1+
b0 !
b0 /
b0 6
b1010 ,
b1010 2
b1010 3
1%
b1 (
#400
0%
b1010 $
b1010 *
b1010 1
b1010 '
b0 (
#420
b1 !
b1 /
b1 6
b1011 ,
b1011 2
b1011 3
1%
b1 (
#440
0%
b1011 $
b1011 *
b1011 1
b1011 '
b0 (
#460
b10 !
b10 /
b10 6
b1100 ,
b1100 2
b1100 3
1%
b1 (
#480
0%
b1100 $
b1100 *
b1100 1
b1100 '
b0 (
#500
b11 !
b11 /
b11 6
b1101 ,
b1101 2
b1101 3
1%
b1 (
#520
0%
b1101 $
b1101 *
b1101 1
b1101 '
b0 (
#540
b100 !
b100 /
b100 6
b1110 ,
b1110 2
b1110 3
1%
b1 (
#560
0%
b1110 $
b1110 *
b1110 1
b1110 '
b0 (
#580
b101 !
b101 /
b101 6
b1111 ,
b1111 2
b1111 3
1%
b1 (
#600
0%
b1111 $
b1111 *
b1111 1
b1111 '
b0 (
#620
b110 !
b110 /
b110 6
07
b0 ,
b0 2
b0 3
1-
1%
b1 (
#640
0"
b0 .
b0 4
0+
b1 !
b1 /
b1 6
0-
b1 ,
b1 2
b1 3
0%
b0 $
b0 *
b0 1
b1 #
b1 )
b1 0
b1 &
b0 '
b0 (
#660
b10 !
b10 /
b10 6
b10 ,
b10 2
b10 3
1%
b1 (
#680
0%
b1 $
b1 *
b1 1
b1 '
b0 (
#700
b11 !
b11 /
b11 6
b11 ,
b11 2
b11 3
1%
b1 (
#720
0%
b10 $
b10 *
b10 1
b10 '
b0 (
#740
b100 !
b100 /
b100 6
b100 ,
b100 2
b100 3
1%
b1 (
#760
0%
b11 $
b11 *
b11 1
b11 '
b0 (
#780
b101 !
b101 /
b101 6
b101 ,
b101 2
b101 3
1%
b1 (
#800
0%
b100 $
b100 *
b100 1
b100 '
b0 (
#820
b110 !
b110 /
b110 6
b110 ,
b110 2
b110 3
1%
b1 (
#840
0%
b101 $
b101 *
b101 1
b101 '
b0 (
#860
b111 !
b111 /
b111 6
b111 ,
b111 2
b111 3
1%
b1 (
#880
0%
b110 $
b110 *
b110 1
b110 '
b0 (
#900
0"
b0 .
b0 4
0+
b1000 !
b1000 /
b1000 6
b1000 ,
b1000 2
b1000 3
1%
b1 (
#920
0%
b111 $
b111 *
b111 1
b111 '
b0 (
#940
b1001 !
b1001 /
b1001 6
b1001 ,
b1001 2
b1001 3
1%
b1 (
#960
0%
b1000 $
b1000 *
b1000 1
b1000 '
b0 (
#980
17
1"
b110 .
b110 4
1+
b0 !
b0 /
b0 6
b1010 ,
b1010 2
b1010 3
1%
b1 (
#1000
0%
b1001 $
b1001 *
b1001 1
b1001 '
b0 (
#1020
b1 !
b1 /
b1 6
b1011 ,
b1011 2
b1011 3
1%
b1 (
#1040
0%
b1010 $
b1010 *
b1010 1
b1010 '
b0 (
#1060
b10 !
b10 /
b10 6
b1100 ,
b1100 2
b1100 3
1%
b1 (
#1080
0%
b1011 $
b1011 *
b1011 1
b1011 '
b0 (
#1100
b11 !
b11 /
b11 6
b1101 ,
b1101 2
b1101 3
1%
b1 (
#1120
0%
b1100 $
b1100 *
b1100 1
b1100 '
b0 (
#1140
b100 !
b100 /
b100 6
b1110 ,
b1110 2
b1110 3
1%
b1 (
#1160
0%
b1101 $
b1101 *
b1101 1
b1101 '
b0 (
#1180
b101 !
b101 /
b101 6
b1111 ,
b1111 2
b1111 3
1%
b1 (
#1200
0%
b1110 $
b1110 *
b1110 1
b1110 '
b0 (
#1220
b110 !
b110 /
b110 6
07
b0 ,
b0 2
b0 3
1-
1%
b1 (
#1240
0%
b1111 $
b1111 *
b1111 1
b1111 '
b0 (
#1260
b111 !
b111 /
b111 6
b1 ,
b1 2
b1 3
1%
b1 (
#1280
0"
b0 .
b0 4
0+
b10 !
b10 /
b10 6
0-
b10 ,
b10 2
b10 3
0%
b0 $
b0 *
b0 1
b10 #
b10 )
b10 0
b10 &
b0 '
b0 (
#1300
b11 !
b11 /
b11 6
b11 ,
b11 2
b11 3
1%
b1 (
#1320
0%
b1 $
b1 *
b1 1
b1 '
b0 (
#1340
b100 !
b100 /
b100 6
b100 ,
b100 2
b100 3
1%
b1 (
#1360
0%
b10 $
b10 *
b10 1
b10 '
b0 (
#1380
b101 !
b101 /
b101 6
b101 ,
b101 2
b101 3
1%
b1 (
#1400
0%
b11 $
b11 *
b11 1
b11 '
b0 (
#1420
b110 !
b110 /
b110 6
b110 ,
b110 2
b110 3
1%
b1 (
#1440
0%
b100 $
b100 *
b100 1
b100 '
b0 (
#1460
b111 !
b111 /
b111 6
b111 ,
b111 2
b111 3
1%
b1 (
#1480
0%
b101 $
b101 *
b101 1
b101 '
b0 (
#1500
0"
b0 .
b0 4
0+
b1000 !
b1000 /
b1000 6
b1000 ,
b1000 2
b1000 3
1%
b1 (
#1520
0%
b110 $
b110 *
b110 1
b110 '
b0 (
#1540
b1001 !
b1001 /
b1001 6
b1001 ,
b1001 2
b1001 3
1%
b1 (
#1560
0%
b111 $
b111 *
b111 1
b111 '
b0 (
#1580
17
1"
b110 .
b110 4
1+
b0 !
b0 /
b0 6
b1010 ,
b1010 2
b1010 3
1%
b1 (
#1600
0%
b1000 $
b1000 *
b1000 1
b1000 '
b0 (
#1620
b1 !
b1 /
b1 6
b1011 ,
b1011 2
b1011 3
1%
b1 (
#1640
0%
b1001 $
b1001 *
b1001 1
b1001 '
b0 (
#1660
b10 !
b10 /
b10 6
b1100 ,
b1100 2
b1100 3
1%
b1 (
#1680
0%
b1010 $
b1010 *
b1010 1
b1010 '
b0 (
#1700
b11 !
b11 /
b11 6
b1101 ,
b1101 2
b1101 3
1%
b1 (
#1720
0%
b1011 $
b1011 *
b1011 1
b1011 '
b0 (
#1740
b100 !
b100 /
b100 6
b1110 ,
b1110 2
b1110 3
1%
b1 (
#1760
0%
b1100 $
b1100 *
b1100 1
b1100 '
b0 (
#1780
b101 !
b101 /
b101 6
b1111 ,
b1111 2
b1111 3
1%
b1 (
#1800
0%
b1101 $
b1101 *
b1101 1
b1101 '
b0 (
#1820
b110 !
b110 /
b110 6
07
b0 ,
b0 2
b0 3
1-
1%
b1 (
#1840
0%
b1110 $
b1110 *
b1110 1
b1110 '
b0 (
#1860
b111 !
b111 /
b111 6
b1 ,
b1 2
b1 3
1%
b1 (
#1880
0%
b1111 $
b1111 *
b1111 1
b1111 '
b0 (
#1900
b1000 !
b1000 /
b1000 6
b10 ,
b10 2
b10 3
1%
b1 (
#1920
0"
b0 .
b0 4
0+
b11 !
b11 /
b11 6
0-
b11 ,
b11 2
b11 3
0%
b0 $
b0 *
b0 1
b11 #
b11 )
b11 0
b11 &
b0 '
b0 (
#1940
b100 !
b100 /
b100 6
b100 ,
b100 2
b100 3
1%
b1 (
#1960
0%
b1 $
b1 *
b1 1
b1 '
b0 (
#1980
b101 !
b101 /
b101 6
b101 ,
b101 2
b101 3
1%
b1 (
#2000
0%
b10 $
b10 *
b10 1
b10 '
b0 (
#2020
b110 !
b110 /
b110 6
b110 ,
b110 2
b110 3
1%
b1 (
#2040
0%
b11 $
b11 *
b11 1
b11 '
b0 (
#2060
b111 !
b111 /
b111 6
b111 ,
b111 2
b111 3
1%
b1 (
#2080
0%
b100 $
b100 *
b100 1
b100 '
b0 (
#2100
0"
b0 .
b0 4
0+
b1000 !
b1000 /
b1000 6
b1000 ,
b1000 2
b1000 3
1%
b1 (
#2120
0%
b101 $
b101 *
b101 1
b101 '
b0 (
#2140
b1001 !
b1001 /
b1001 6
b1001 ,
b1001 2
b1001 3
1%
b1 (
#2160
0%
b110 $
b110 *
b110 1
b110 '
b0 (
#2180
17
1"
b110 .
b110 4
1+
b0 !
b0 /
b0 6
b1010 ,
b1010 2
b1010 3
1%
b1 (
#2200
0%
b111 $
b111 *
b111 1
b111 '
b0 (
#2220
b1 !
b1 /
b1 6
b1011 ,
b1011 2
b1011 3
1%
b1 (
#2240
0%
b1000 $
b1000 *
b1000 1
b1000 '
b0 (
#2260
b10 !
b10 /
b10 6
b1100 ,
b1100 2
b1100 3
1%
b1 (
#2280
0%
b1001 $
b1001 *
b1001 1
b1001 '
b0 (
#2300
b11 !
b11 /
b11 6
b1101 ,
b1101 2
b1101 3
1%
b1 (
#2320
0%
b1010 $
b1010 *
b1010 1
b1010 '
b0 (
#2340
b100 !
b100 /
b100 6
b1110 ,
b1110 2
b1110 3
1%
b1 (
#2360
0%
b1011 $
b1011 *
b1011 1
b1011 '
b0 (
#2380
b101 !
b101 /
b101 6
b1111 ,
b1111 2
b1111 3
1%
b1 (
#2400
0%
b1100 $
b1100 *
b1100 1
b1100 '
b0 (
#2420
b110 !
b110 /
b110 6
07
b0 ,
b0 2
b0 3
1-
1%
b1 (
#2440
0%
b1101 $
b1101 *
b1101 1
b1101 '
b0 (
#2460
b111 !
b111 /
b111 6
b1 ,
b1 2
b1 3
1%
b1 (
#2480
0%
b1110 $
b1110 *
b1110 1
b1110 '
b0 (
#2500
b1000 !
b1000 /
b1000 6
b10 ,
b10 2
b10 3
1%
b1 (
#2520
0%
b1111 $
b1111 *
b1111 1
b1111 '
b0 (
#2540
b1001 !
b1001 /
b1001 6
b11 ,
b11 2
b11 3
1%
b1 (
#2560
0"
b0 .
b0 4
0+
b100 !
b100 /
b100 6
0-
b100 ,
b100 2
b100 3
0%
b0 $
b0 *
b0 1
b100 #
b100 )
b100 0
b100 &
b0 '
b0 (
#2580
b101 !
b101 /
b101 6
b101 ,
b101 2
b101 3
1%
b1 (
#2600
0%
b1 $
b1 *
b1 1
b1 '
b0 (
#2620
b110 !
b110 /
b110 6
b110 ,
b110 2
b110 3
1%
b1 (
#2640
0%
b10 $
b10 *
b10 1
b10 '
b0 (
#2660
b111 !
b111 /
b111 6
b111 ,
b111 2
b111 3
1%
b1 (
#2680
0%
b11 $
b11 *
b11 1
b11 '
b0 (
#2700
0"
b0 .
b0 4
0+
b1000 !
b1000 /
b1000 6
b1000 ,
b1000 2
b1000 3
1%
b1 (
#2720
0%
b100 $
b100 *
b100 1
b100 '
b0 (
#2740
b1001 !
b1001 /
b1001 6
b1001 ,
b1001 2
b1001 3
1%
b1 (
#2760
0%
b101 $
b101 *
b101 1
b101 '
b0 (
#2780
17
1"
b110 .
b110 4
1+
b0 !
b0 /
b0 6
b1010 ,
b1010 2
b1010 3
1%
b1 (
#2800
0%
b110 $
b110 *
b110 1
b110 '
b0 (
#2820
b1 !
b1 /
b1 6
b1011 ,
b1011 2
b1011 3
1%
b1 (
#2840
0%
b111 $
b111 *
b111 1
b111 '
b0 (
#2860
b10 !
b10 /
b10 6
b1100 ,
b1100 2
b1100 3
1%
b1 (
#2880
0%
b1000 $
b1000 *
b1000 1
b1000 '
b0 (
#2900
b11 !
b11 /
b11 6
b1101 ,
b1101 2
b1101 3
1%
b1 (
#2920
0%
b1001 $
b1001 *
b1001 1
b1001 '
b0 (
#2940
b100 !
b100 /
b100 6
b1110 ,
b1110 2
b1110 3
1%
b1 (
#2960
0%
b1010 $
b1010 *
b1010 1
b1010 '
b0 (
#2980
b101 !
b101 /
b101 6
b1111 ,
b1111 2
b1111 3
1%
b1 (
#3000
0%
b1011 $
b1011 *
b1011 1
b1011 '
b0 (
#3020
b110 !
b110 /
b110 6
07
b0 ,
b0 2
b0 3
1-
1%
b1 (
#3040
0%
b1100 $
b1100 *
b1100 1
b1100 '
b0 (
#3060
b111 !
b111 /
b111 6
b1 ,
b1 2
b1 3
1%
b1 (
#3080
0%
b1101 $
b1101 *
b1101 1
b1101 '
b0 (
#3100
b1000 !
b1000 /
b1000 6
b10 ,
b10 2
b10 3
1%
b1 (
#3120
0%
b1110 $
b1110 *
b1110 1
b1110 '
b0 (
#3140
b1001 !
b1001 /
b1001 6
b11 ,
b11 2
b11 3
1%
b1 (
#3160
0%
b1111 $
b1111 *
b1111 1
b1111 '
b0 (
#3180
b1010 !
b1010 /
b1010 6
b100 ,
b100 2
b100 3
1%
b1 (
#3200
0"
b0 .
b0 4
0+
b101 !
b101 /
b101 6
0-
b101 ,
b101 2
b101 3
0%
b0 $
b0 *
b0 1
b101 #
b101 )
b101 0
b101 &
b0 '
b0 (
#3220
b110 !
b110 /
b110 6
b110 ,
b110 2
b110 3
1%
b1 (
#3240
0%
b1 $
b1 *
b1 1
b1 '
b0 (
#3260
b111 !
b111 /
b111 6
b111 ,
b111 2
b111 3
1%
b1 (
#3280
0%
b10 $
b10 *
b10 1
b10 '
b0 (
#3300
0"
b0 .
b0 4
0+
b1000 !
b1000 /
b1000 6
b1000 ,
b1000 2
b1000 3
1%
b1 (
#3320
0%
b11 $
b11 *
b11 1
b11 '
b0 (
#3340
b1001 !
b1001 /
b1001 6
b1001 ,
b1001 2
b1001 3
1%
b1 (
#3360
0%
b100 $
b100 *
b100 1
b100 '
b0 (
#3380
17
1"
b110 .
b110 4
1+
b0 !
b0 /
b0 6
b1010 ,
b1010 2
b1010 3
1%
b1 (
#3400
0%
b101 $
b101 *
b101 1
b101 '
b0 (
#3420
b1 !
b1 /
b1 6
b1011 ,
b1011 2
b1011 3
1%
b1 (
#3440
0%
b110 $
b110 *
b110 1
b110 '
b0 (
#3460
b10 !
b10 /
b10 6
b1100 ,
b1100 2
b1100 3
1%
b1 (
#3480
0%
b111 $
b111 *
b111 1
b111 '
b0 (
#3500
b11 !
b11 /
b11 6
b1101 ,
b1101 2
b1101 3
1%
b1 (
#3520
0%
b1000 $
b1000 *
b1000 1
b1000 '
b0 (
#3540
b100 !
b100 /
b100 6
b1110 ,
b1110 2
b1110 3
1%
b1 (
#3560
0%
b1001 $
b1001 *
b1001 1
b1001 '
b0 (
#3580
b101 !
b101 /
b101 6
b1111 ,
b1111 2
b1111 3
1%
b1 (
#3600
0%
b1010 $
b1010 *
b1010 1
b1010 '
b0 (
#3620
b110 !
b110 /
b110 6
07
b0 ,
b0 2
b0 3
1-
1%
b1 (
#3640
0%
b1011 $
b1011 *
b1011 1
b1011 '
b0 (
#3660
b111 !
b111 /
b111 6
b1 ,
b1 2
b1 3
1%
b1 (
#3680
0%
b1100 $
b1100 *
b1100 1
b1100 '
b0 (
#3700
b1000 !
b1000 /
b1000 6
b10 ,
b10 2
b10 3
1%
b1 (
#3720
0%
b1101 $
b1101 *
b1101 1
b1101 '
b0 (
#3740
b1001 !
b1001 /
b1001 6
b11 ,
b11 2
b11 3
1%
b1 (
#3760
0%
b1110 $
b1110 *
b1110 1
b1110 '
b0 (
#3780
b1010 !
b1010 /
b1010 6
b100 ,
b100 2
b100 3
1%
b1 (
#3800
0%
b1111 $
b1111 *
b1111 1
b1111 '
b0 (
#3820
b1011 !
b1011 /
b1011 6
b101 ,
b101 2
b101 3
1%
b1 (
#3840
0"
b0 .
b0 4
0+
b110 !
b110 /
b110 6
0-
b110 ,
b110 2
b110 3
0%
b0 $
b0 *
b0 1
b110 #
b110 )
b110 0
b110 &
b0 '
b0 (
#3860
b111 !
b111 /
b111 6
b111 ,
b111 2
b111 3
1%
b1 (
#3880
0%
b1 $
b1 *
b1 1
b1 '
b0 (
#3900
0"
b0 .
b0 4
0+
b1000 !
b1000 /
b1000 6
b1000 ,
b1000 2
b1000 3
1%
b1 (
#3920
0%
b10 $
b10 *
b10 1
b10 '
b0 (
#3940
b1001 !
b1001 /
b1001 6
b1001 ,
b1001 2
b1001 3
1%
b1 (
#3960
0%
b11 $
b11 *
b11 1
b11 '
b0 (
#3980
17
1"
b110 .
b110 4
1+
b0 !
b0 /
b0 6
b1010 ,
b1010 2
b1010 3
1%
b1 (
#4000
0%
b100 $
b100 *
b100 1
b100 '
b0 (
#4020
b1 !
b1 /
b1 6
b1011 ,
b1011 2
b1011 3
1%
b1 (
#4040
0%
b101 $
b101 *
b101 1
b101 '
b0 (
#4060
b10 !
b10 /
b10 6
b1100 ,
b1100 2
b1100 3
1%
b1 (
#4080
0%
b110 $
b110 *
b110 1
b110 '
b0 (
#4100
b11 !
b11 /
b11 6
b1101 ,
b1101 2
b1101 3
1%
b1 (
#4120
0%
b111 $
b111 *
b111 1
b111 '
b0 (
#4140
b100 !
b100 /
b100 6
b1110 ,
b1110 2
b1110 3
1%
b1 (
#4160
0%
b1000 $
b1000 *
b1000 1
b1000 '
b0 (
#4180
b101 !
b101 /
b101 6
b1111 ,
b1111 2
b1111 3
1%
b1 (
#4200
0%
b1001 $
b1001 *
b1001 1
b1001 '
b0 (
#4220
b110 !
b110 /
b110 6
07
b0 ,
b0 2
b0 3
1-
1%
b1 (
#4240
0%
b1010 $
b1010 *
b1010 1
b1010 '
b0 (
#4260
b111 !
b111 /
b111 6
b1 ,
b1 2
b1 3
1%
b1 (
#4280
0%
b1011 $
b1011 *
b1011 1
b1011 '
b0 (
#4300
b1000 !
b1000 /
b1000 6
b10 ,
b10 2
b10 3
1%
b1 (
#4320
0%
b1100 $
b1100 *
b1100 1
b1100 '
b0 (
#4340
b1001 !
b1001 /
b1001 6
b11 ,
b11 2
b11 3
1%
b1 (
#4360
0%
b1101 $
b1101 *
b1101 1
b1101 '
b0 (
#4380
b1010 !
b1010 /
b1010 6
b100 ,
b100 2
b100 3
1%
b1 (
#4400
0%
b1110 $
b1110 *
b1110 1
b1110 '
b0 (
#4420
b1011 !
b1011 /
b1011 6
b101 ,
b101 2
b101 3
1%
b1 (
#4440
0%
b1111 $
b1111 *
b1111 1
b1111 '
b0 (
#4460
b1100 !
b1100 /
b1100 6
b110 ,
b110 2
b110 3
1%
b1 (
#4480
0"
b0 .
b0 4
0+
b111 !
b111 /
b111 6
0-
b111 ,
b111 2
b111 3
0%
b0 $
b0 *
b0 1
b111 #
b111 )
b111 0
b111 &
b0 '
b0 (
#4500
0"
b0 .
b0 4
0+
b1000 !
b1000 /
b1000 6
b1000 ,
b1000 2
b1000 3
1%
b1 (
#4520
0%
b1 $
b1 *
b1 1
b1 '
b0 (
#4540
b1001 !
b1001 /
b1001 6
b1001 ,
b1001 2
b1001 3
1%
b1 (
#4560
0%
b10 $
b10 *
b10 1
b10 '
b0 (
#4580
17
1"
b110 .
b110 4
1+
b0 !
b0 /
b0 6
b1010 ,
b1010 2
b1010 3
1%
b1 (
#4600
0%
b11 $
b11 *
b11 1
b11 '
b0 (
#4620
b1 !
b1 /
b1 6
b1011 ,
b1011 2
b1011 3
1%
b1 (
#4640
0%
b100 $
b100 *
b100 1
b100 '
b0 (
#4660
b10 !
b10 /
b10 6
b1100 ,
b1100 2
b1100 3
1%
b1 (
#4680
0%
b101 $
b101 *
b101 1
b101 '
b0 (
#4700
b11 !
b11 /
b11 6
b1101 ,
b1101 2
b1101 3
1%
b1 (
#4720
0%
b110 $
b110 *
b110 1
b110 '
b0 (
#4740
b100 !
b100 /
b100 6
b1110 ,
b1110 2
b1110 3
1%
b1 (
#4760
0%
b111 $
b111 *
b111 1
b111 '
b0 (
#4780
b101 !
b101 /
b101 6
b1111 ,
b1111 2
b1111 3
1%
b1 (
#4800
0%
b1000 $
b1000 *
b1000 1
b1000 '
b0 (
#4820
b110 !
b110 /
b110 6
07
b0 ,
b0 2
b0 3
1-
1%
b1 (
#4840
0%
b1001 $
b1001 *
b1001 1
b1001 '
b0 (
#4860
b111 !
b111 /
b111 6
b1 ,
b1 2
b1 3
1%
b1 (
#4880
0%
b1010 $
b1010 *
b1010 1
b1010 '
b0 (
#4900
b1000 !
b1000 /
b1000 6
b10 ,
b10 2
b10 3
1%
b1 (
#4920
0%
b1011 $
b1011 *
b1011 1
b1011 '
b0 (
#4940
b1001 !
b1001 /
b1001 6
b11 ,
b11 2
b11 3
1%
b1 (
#4960
0%
b1100 $
b1100 *
b1100 1
b1100 '
b0 (
#4980
b1010 !
b1010 /
b1010 6
b100 ,
b100 2
b100 3
1%
b1 (
#5000
0%
b1101 $
b1101 *
b1101 1
b1101 '
b0 (
#5020
b1011 !
b1011 /
b1011 6
b101 ,
b101 2
b101 3
1%
b1 (
#5040
0%
b1110 $
b1110 *
b1110 1
b1110 '
b0 (
#5060
b1100 !
b1100 /
b1100 6
b110 ,
b110 2
b110 3
1%
b1 (
#5080
0%
b1111 $
b1111 *
b1111 1
b1111 '
b0 (
#5100
b1101 !
b1101 /
b1101 6
b111 ,
b111 2
b111 3
1%
b1 (
#5120
0"
b0 .
b0 4
0+
b1000 !
b1000 /
b1000 6
0-
b1000 ,
b1000 2
b1000 3
0%
b0 $
b0 *
b0 1
b1000 #
b1000 )
b1000 0
b1000 &
b0 '
b0 (
#5140
b1001 !
b1001 /
b1001 6
b1001 ,
b1001 2
b1001 3
1%
b1 (
#5160
0%
b1 $
b1 *
b1 1
b1 '
b0 (
#5180
17
1"
b110 .
b110 4
1+
b0 !
b0 /
b0 6
b1010 ,
b1010 2
b1010 3
1%
b1 (
#5200
0%
b10 $
b10 *
b10 1
b10 '
b0 (
#5220
b1 !
b1 /
b1 6
b1011 ,
b1011 2
b1011 3
1%
b1 (
#5240
0%
b11 $
b11 *
b11 1
b11 '
b0 (
#5260
b10 !
b10 /
b10 6
b1100 ,
b1100 2
b1100 3
1%
b1 (
#5280
0%
b100 $
b100 *
b100 1
b100 '
b0 (
#5300
b11 !
b11 /
b11 6
b1101 ,
b1101 2
b1101 3
1%
b1 (
#5320
0%
b101 $
b101 *
b101 1
b101 '
b0 (
#5340
b100 !
b100 /
b100 6
b1110 ,
b1110 2
b1110 3
1%
b1 (
#5360
0%
b110 $
b110 *
b110 1
b110 '
b0 (
#5380
b101 !
b101 /
b101 6
b1111 ,
b1111 2
b1111 3
1%
b1 (
#5400
0%
b111 $
b111 *
b111 1
b111 '
b0 (
#5420
b110 !
b110 /
b110 6
07
b0 ,
b0 2
b0 3
1-
1%
b1 (
#5440
0%
b1000 $
b1000 *
b1000 1
b1000 '
b0 (
#5460
b111 !
b111 /
b111 6
b1 ,
b1 2
b1 3
1%
b1 (
#5480
0%
b1001 $
b1001 *
b1001 1
b1001 '
b0 (
#5500
b1000 !
b1000 /
b1000 6
b10 ,
b10 2
b10 3
1%
b1 (
#5520
0%
b1010 $
b1010 *
b1010 1
b1010 '
b0 (
#5540
b1001 !
b1001 /
b1001 6
b11 ,
b11 2
b11 3
1%
b1 (
#5560
0%
b1011 $
b1011 *
b1011 1
b1011 '
b0 (
#5580
b1010 !
b1010 /
b1010 6
b100 ,
b100 2
b100 3
1%
b1 (
#5600
0%
b1100 $
b1100 *
b1100 1
b1100 '
b0 (
#5620
b1011 !
b1011 /
b1011 6
b101 ,
b101 2
b101 3
1%
b1 (
#5640
0%
b1101 $
b1101 *
b1101 1
b1101 '
b0 (
#5660
b1100 !
b1100 /
b1100 6
b110 ,
b110 2
b110 3
1%
b1 (
#5680
0%
b1110 $
b1110 *
b1110 1
b1110 '
b0 (
#5700
b1101 !
b1101 /
b1101 6
b111 ,
b111 2
b111 3
1%
b1 (
#5720
0%
b1111 $
b1111 *
b1111 1
b1111 '
b0 (
#5740
b1110 !
b1110 /
b1110 6
b1000 ,
b1000 2
b1000 3
1%
b1 (
#5760
0"
b0 .
b0 4
0+
b1001 !
b1001 /
b1001 6
0-
b1001 ,
b1001 2
b1001 3
0%
b0 $
b0 *
b0 1
b1001 #
b1001 )
b1001 0
b1001 &
b0 '
b0 (
#5780
17
1"
b110 .
b110 4
1+
b0 !
b0 /
b0 6
b1010 ,
b1010 2
b1010 3
1%
b1 (
#5800
0%
b1 $
b1 *
b1 1
b1 '
b0 (
#5820
b1 !
b1 /
b1 6
b1011 ,
b1011 2
b1011 3
1%
b1 (
#5840
0%
b10 $
b10 *
b10 1
b10 '
b0 (
#5860
b10 !
b10 /
b10 6
b1100 ,
b1100 2
b1100 3
1%
b1 (
#5880
0%
b11 $
b11 *
b11 1
b11 '
b0 (
#5900
b11 !
b11 /
b11 6
b1101 ,
b1101 2
b1101 3
1%
b1 (
#5920
0%
b100 $
b100 *
b100 1
b100 '
b0 (
#5940
b100 !
b100 /
b100 6
b1110 ,
b1110 2
b1110 3
1%
b1 (
#5960
0%
b101 $
b101 *
b101 1
b101 '
b0 (
#5980
b101 !
b101 /
b101 6
b1111 ,
b1111 2
b1111 3
1%
b1 (
#6000
0%
b110 $
b110 *
b110 1
b110 '
b0 (
#6020
b110 !
b110 /
b110 6
07
b0 ,
b0 2
b0 3
1-
1%
b1 (
#6040
0%
b111 $
b111 *
b111 1
b111 '
b0 (
#6060
b111 !
b111 /
b111 6
b1 ,
b1 2
b1 3
1%
b1 (
#6080
0%
b1000 $
b1000 *
b1000 1
b1000 '
b0 (
#6100
b1000 !
b1000 /
b1000 6
b10 ,
b10 2
b10 3
1%
b1 (
#6120
0%
b1001 $
b1001 *
b1001 1
b1001 '
b0 (
#6140
b1001 !
b1001 /
b1001 6
b11 ,
b11 2
b11 3
1%
b1 (
#6160
0%
b1010 $
b1010 *
b1010 1
b1010 '
b0 (
#6180
b1010 !
b1010 /
b1010 6
b100 ,
b100 2
b100 3
1%
b1 (
#6200
0%
b1011 $
b1011 *
b1011 1
b1011 '
b0 (
#6220
b1011 !
b1011 /
b1011 6
b101 ,
b101 2
b101 3
1%
b1 (
#6240
0%
b1100 $
b1100 *
b1100 1
b1100 '
b0 (
#6260
b1100 !
b1100 /
b1100 6
b110 ,
b110 2
b110 3
1%
b1 (
#6280
0%
b1101 $
b1101 *
b1101 1
b1101 '
b0 (
#6300
b1101 !
b1101 /
b1101 6
b111 ,
b111 2
b111 3
1%
b1 (
#6320
0%
b1110 $
b1110 *
b1110 1
b1110 '
b0 (
#6340
b1110 !
b1110 /
b1110 6
b1000 ,
b1000 2
b1000 3
1%
b1 (
#6360
0%
b1111 $
b1111 *
b1111 1
b1111 '
b0 (
#6380
b1111 !
b1111 /
b1111 6
b1001 ,
b1001 2
b1001 3
1%
b1 (
