LAB 7/Q3/question3.v
module question3;
    reg clk = 0;
    reg reset = 0;
    reg j = 0;
    reg k = 0;
    reg q = 0;

    always @(posedge clk) begin
        if (reset)
            q <= 1'b0;
        else begin
            case ({j, k})
                2'b00: q <= q;
                2'b01: q <= 1'b0;
                2'b10: q <= 1'b1;
                2'b11: q <= ~q;
            endcase
        end
    end

endmodule

LAB 7/Q3/question3_tb.v
`include "question3.v"
`timescale 1ns/1ns

module question3_tb();

question3 q3();

initial
begin
    $dumpfile("question3.vcd");
    $dumpvars(0, question3_tb);

    #10 q3.reset = 1; q3.j = 0; q3.k = 0;
    #15 q3.reset = 0; q3.j = 1; q3.k = 0;
    #15 q3.j = 0; q3.k = 1;
    #15 q3.j = 1; q3.k = 1;
    #15 q3.j = 0; q3.k = 0;
    #10 q3.reset = 1;
    #10 q3.reset = 0; q3.j = 1; q3.k = 1;
    #20;
    
    $display("Test Complete");
    $finish;
end

always #5 q3.clk = ~q3.clk;

endmodule

LAB 7/Q3/question3.vcd
$date
	Sat Sep 12 09:32:12 2026
$end
$version
	Icarus Verilog
$end
$timescale
	1ns
$end
$scope module question3_tb $end
$scope module q3 $end
$var reg 1 ! clk $end
$var reg 1 " j $end
$var reg 1 # k $end
$var reg 1 $ q $end
$var reg 1 % reset $end
$upscope $end
$upscope $end
$enddefinitions $end
#0
$dumpvars
0%
0$
0#
0"
0!
$end
#5
1!
#10
0!
1%
#15
1!
#20
0!
#25
1$
1!
1"
0%
#30
0!
#35
1!
#40
0!
1#
0"
#45
0$
1!
#50
0!
#55
1$
1!
1"
#60
0!
#65
0$
1!
#70
0!
0#
0"
#75
1!
#80
0!
1%
#85
1!
#90
0!
1#
1"
0%
#95
1$
1!
#100
0!
#105
0$
1!
