LAB 6/Q3/question3.v
module question3(W, E, Y);
    input [3:0] W;
    input E;
    output [15:0] Y;

    wire [3:0] sub_E;

    assign sub_E[0] = E & (W[3:2] == 2'b00);
    assign sub_E[1] = E & (W[3:2] == 2'b01);
    assign sub_E[2] = E & (W[3:2] == 2'b10);
    assign sub_E[3] = E & (W[3:2] == 2'b11);

    decoder2to4 d0(W[1:0], sub_E[0], Y[3:0]);
    decoder2to4 d1(W[1:0], sub_E[1], Y[7:4]);
    decoder2to4 d2(W[1:0], sub_E[2], Y[11:8]);
    decoder2to4 d3(W[1:0], sub_E[3], Y[15:12]);
endmodule

module decoder2to4(A, E, Y);
    input [1:0] A;
    input E;
    output reg [3:0] Y;

    always @(*) begin
        if (!E) begin
            Y = 4'b1111;
        end else begin
            case (A)
                2'b00: Y = 4'b1110;
                2'b01: Y = 4'b1101;
                2'b10: Y = 4'b1011;
                2'b11: Y = 4'b0111;
                default: Y = 4'b1111;
            endcase
        end
    end
endmodule

LAB 6/Q3/question3_tb.v
`include "question3.v"
`timescale 1ns/1ns

module question3_tb();
    reg [3:0] W;
    reg E;
    wire [15:0] Y;

    integer i, j;
    question3 uut(W, E, Y);

    initial begin
        $dumpfile("question3.vcd");
        $dumpvars(0, question3_tb);
        for (i = 0; i <= 1; i = i + 1) begin
            for (j = 0; j <= 15; j = j + 1) begin
                E = i;
                W = j;
                #20;
            end
        end
        $display("Test Complete");
    end
endmodule

LAB 6/Q3/question3.vcd
$date
	Wed Sep  2 10:06:31 2026
$end
$version
	Icarus Verilog
$end
$timescale
	1ns
$end
$scope module question3_tb $end
$var wire 16 ! Y [15:0] $end
$var reg 1 " E $end
$var reg 4 # W [3:0] $end
$var integer 32 $ i [31:0] $end
$var integer 32 % j [31:0] $end
$scope module uut $end
$var wire 1 " E $end
$var wire 4 & W [3:0] $end
$var wire 4 ' sub_E [3:0] $end
$var wire 16 ( Y [15:0] $end
$scope module d0 $end
$var wire 2 ) A [1:0] $end
$var wire 1 * E $end
$var reg 4 + Y [3:0] $end
$upscope $end
$scope module d1 $end
$var wire 2 , A [1:0] $end
$var wire 1 - E $end
$var reg 4 . Y [3:0] $end
$upscope $end
$scope module d2 $end
$var wire 2 / A [1:0] $end
$var wire 1 0 E $end
$var reg 4 1 Y [3:0] $end
$upscope $end
$scope module d3 $end
$var wire 2 2 A [1:0] $end
$var wire 1 3 E $end
$var reg 4 4 Y [3:0] $end
$upscope $end
$upscope $end
$upscope $end
$enddefinitions $end
#0
$dumpvars
b1111 4
03
b0 2
b1111 1
00
b0 /
b1111 .
0-
b0 ,
b1111 +
0*
b0 )
b1111111111111111 (
b0 '
b0 &
b0 %
b0 $
b0 #
0"
b1111111111111111 !
$end
#20
b1 )
b1 ,
b1 /
b1 2
b1 #
b1 &
b1 %
#40
b10 )
b10 ,
b10 /
b10 2
b10 #
b10 &
b10 %
#60
b11 )
b11 ,
b11 /
b11 2
b11 #
b11 &
b11 %
#80
b0 )
b0 ,
b0 /
b0 2
b100 #
b100 &
b100 %
#100
b1 )
b1 ,
b1 /
b1 2
b101 #
b101 &
b101 %
#120
b10 )
b10 ,
b10 /
b10 2
b110 #
b110 &
b110 %
#140
b11 )
b11 ,
b11 /
b11 2
b111 #
b111 &
b111 %
#160
b0 )
b0 ,
b0 /
b0 2
b1000 #
b1000 &
b1000 %
#180
b1 )
b1 ,
b1 /
b1 2
b1001 #
b1001 &
b1001 %
#200
b10 )
b10 ,
b10 /
b10 2
b1010 #
b1010 &
b1010 %
#220
b11 )
b11 ,
b11 /
b11 2
b1011 #
b1011 &
b1011 %
#240
b0 )
b0 ,
b0 /
b0 2
b1100 #
b1100 &
b1100 %
#260
b1 )
b1 ,
b1 /
b1 2
b1101 #
b1101 &
b1101 %
#280
b10 )
b10 ,
b10 /
b10 2
b1110 #
b1110 &
b1110 %
#300
b11 )
b11 ,
b11 /
b11 2
b1111 #
b1111 &
b1111 %
#320
b1110 +
1*
b1111111111111110 !
b1111111111111110 (
b1111 4
03
b0 )
b0 ,
b0 /
b0 2
b1 '
b0 #
b0 &
1"
b1 $
b0 %
#340
b1111111111111101 !
b1111111111111101 (
b1101 +
b1 )
b1 ,
b1 /
b1 2
b1 #
b1 &
b1 %
#360
b1111111111111011 !
b1111111111111011 (
b1011 +
b10 )
b10 ,
b10 /
b10 2
b10 #
b10 &
b10 %
#380
b1111111111110111 !
b1111111111110111 (
b111 +
b11 )
b11 ,
b11 /
b11 2
b11 #
b11 &
b11 %
#400
b1110 .
0*
1-
b10 '
b1111111111101111 !
b1111111111101111 (
b1111 +
b0 )
b0 ,
b0 /
b0 2
b100 #
b100 &
b100 %
#420
b1111111111011111 !
b1111111111011111 (
b1101 .
b1 )
b1 ,
b1 /
b1 2
b101 #
b101 &
b101 %
#440
b1111111110111111 !
b1111111110111111 (
b1011 .
b10 )
b10 ,
b10 /
b10 2
b110 #
b110 &
b110 %
#460
b1111111101111111 !
b1111111101111111 (
b111 .
b11 )
b11 ,
b11 /
b11 2
b111 #
b111 &
b111 %
#480
b1110 1
0-
10
b100 '
b1111111011111111 !
b1111111011111111 (
b1111 .
b0 )
b0 ,
b0 /
b0 2
b1000 #
b1000 &
b1000 %
#500
b1111110111111111 !
b1111110111111111 (
b1101 1
b1 )
b1 ,
b1 /
b1 2
b1001 #
b1001 &
b1001 %
#520
b1111101111111111 !
b1111101111111111 (
b1011 1
b10 )
b10 ,
b10 /
b10 2
b1010 #
b1010 &
b1010 %
#540
b1111011111111111 !
b1111011111111111 (
b111 1
b11 )
b11 ,
b11 /
b11 2
b1011 #
b1011 &
b1011 %
#560
b1110 4
00
13
b1000 '
b1110111111111111 !
b1110111111111111 (
b1111 1
b0 )
b0 ,
b0 /
b0 2
b1100 #
b1100 &
b1100 %
#580
b1101111111111111 !
b1101111111111111 (
b1101 4
b1 )
b1 ,
b1 /
b1 2
b1101 #
b1101 &
b1101 %
#600
b1011111111111111 !
b1011111111111111 (
b1011 4
b10 )
b10 ,
b10 /
b10 2
b1110 #
b1110 &
b1110 %
#620
b111111111111111 !
b111111111111111 (
b111 4
b11 )
b11 ,
b11 /
b11 2
b1111 #
b1111 &
b1111 %
#640
b10 $
b10000 %
