LAB 6/Q4/question4.v
module question4(D, Y, valid);
    input [3:0] D;
    output reg [1:0] Y;
    output reg valid;

    always @(*) begin
        casex (D)
            4'b1xxx: begin Y = 2'b11; valid = 1'b1; end
            4'b01xx: begin Y = 2'b10; valid = 1'b1; end
            4'b001x: begin Y = 2'b01; valid = 1'b1; end
            4'b0001: begin Y = 2'b00; valid = 1'b1; end
            default: begin Y = 2'b00; valid = 1'b0; end
        endcase
    end
endmodule

LAB 6/Q4/question4_tb.v
`include "question4.v"
`timescale 1ns/1ns

module question4_tb();
    reg [3:0] D;
    wire [1:0] Y;
    wire valid;

    integer i;
    question4 uut(D, Y, valid);

    initial begin
        $dumpfile("question4.vcd");
        $dumpvars(0, question4_tb);
        for (i = 0; i <= 15; i = i + 1) begin
            D = i;
            #20;
        end
        $display("Test Complete");
    end
endmodule

LAB 6/Q4/question4.vcd
$date
	Wed Sep  2 10:07:19 2026
$end
$version
	Icarus Verilog
$end
$timescale
	1ns
$end
$scope module question4_tb $end
$var wire 1 ! valid $end
$var wire 2 " Y [1:0] $end
$var reg 4 # D [3:0] $end
$var integer 32 $ i [31:0] $end
$scope module uut $end
$var wire 4 % D [3:0] $end
$var reg 2 & Y [1:0] $end
$var reg 1 ! valid $end
$upscope $end
$upscope $end
$enddefinitions $end
#0
$dumpvars
b0 &
b0 %
b0 $
b0 #
b0 "
0!
$end
#20
1!
b1 #
b1 %
b1 $
#40
b1 "
b1 &
b10 #
b10 %
b10 $
#60
b11 #
b11 %
b11 $
#80
b10 "
b10 &
b100 #
b100 %
b100 $
#100
b101 #
b101 %
b101 $
#120
b110 #
b110 %
b110 $
#140
b111 #
b111 %
b111 $
#160
b11 "
b11 &
b1000 #
b1000 %
b1000 $
#180
b1001 #
b1001 %
b1001 $
#200
b1010 #
b1010 %
b1010 $
#220
b1011 #
b1011 %
b1011 $
#240
b1100 #
b1100 %
b1100 $
#260
b1101 #
b1101 %
b1101 $
#280
b1110 #
b1110 %
b1110 $
#300
b1111 #
b1111 %
b1111 $
#320
b10000 $
