LAB 4/q2/question2.v
module question2(x, y, sum, carryout, control);
input [3:0] x;
input [3:0] y;
input control;
output [3:0] sum;
output [3:0] carryout;

fulladd stage0(carryout[0], sum[0], x[0], y[0], control, control);
fulladd stage1(carryout[1], sum[1], x[1], y[1], control, carryout[0]);
fulladd stage2(carryout[2], sum[2], x[2], y[2], control, carryout[1]);
fulladd stage3(carryout[3], sum[3], x[3], y[3], control, carryout[2]);
endmodule


module fulladd(carryout, sum, x, y, control, carryin);
input x,y,control,carryin;
output carryout, sum;

assign carryout = x&(y^control) | x&carryin | (y^control)&carryin;
assign sum = x^(y^control)^carryin;

endmodule

LAB 4/q2/question2_tb.v
`timescale 1ns/1ns
`include "question2.v"

module question2_tb();

reg [3:0] x;
reg [3:0] y;
reg control;
wire [3:0] sum;
wire [3:0] carryout;

integer i, j, k;
question2 q2(x, y, sum, carryout, control);
initial
begin

	$dumpfile("question2.vcd");
	$dumpvars(0, question2_tb);
	for (k = 0; k < 2; k = k + 1) begin
	    for (i = 0; i < 16; i = i + 1) begin
		for (j = 0; j < 16; j = j + 1) begin
			x = i;
			y = j;
			control = k;
			#20;
		    end
		end
	    end	
	
	
	$display("Test Complete!");
	
end
endmodule

LAB 4/q2/question2.vcd
$date
	Sat Aug 22 10:24:21 2026
$end
$version
	Icarus Verilog
$end
$timescale
	1ns
$end
$scope module question2_tb $end
$var wire 4 ! sum [3:0] $end
$var wire 4 " carryout [3:0] $end
$var reg 1 # control $end
$var reg 4 $ x [3:0] $end
$var reg 4 % y [3:0] $end
$var integer 32 & i [31:0] $end
$var integer 32 ' j [31:0] $end
$var integer 32 ( k [31:0] $end
$scope module q2 $end
$var wire 1 # control $end
$var wire 4 ) x [3:0] $end
$var wire 4 * y [3:0] $end
$var wire 4 + sum [3:0] $end
$var wire 4 , carryout [3:0] $end
$scope module stage0 $end
$var wire 1 # carryin $end
$var wire 1 - carryout $end
$var wire 1 # control $end
$var wire 1 . sum $end
$var wire 1 / x $end
$var wire 1 0 y $end
$upscope $end
$scope module stage1 $end
$var wire 1 1 carryin $end
$var wire 1 2 carryout $end
$var wire 1 # control $end
$var wire 1 3 sum $end
$var wire 1 4 x $end
$var wire 1 5 y $end
$upscope $end
$scope module stage2 $end
$var wire 1 6 carryin $end
$var wire 1 7 carryout $end
$var wire 1 # control $end
$var wire 1 8 sum $end
$var wire 1 9 x $end
$var wire 1 : y $end
$upscope $end
$scope module stage3 $end
$var wire 1 ; carryin $end
$var wire 1 < carryout $end
$var wire 1 # control $end
$var wire 1 = sum $end
$var wire 1 > x $end
$var wire 1 ? y $end
$upscope $end
$upscope $end
$upscope $end
$enddefinitions $end
#0
$dumpvars
0?
0>
0=
0<
0;
0:
09
08
07
06
05
04
03
02
01
00
0/
0.
0-
b0 ,
b0 +
b0 *
b0 )
b0 (
b0 '
b0 &
b0 %
b0 $
0#
b0 "
b0 !
$end
#20
b1 !
b1 +
1.
10
b1 %
b1 *
b1 '
#40
0.
b10 !
b10 +
13
00
15
b10 %
b10 *
b10 '
#60
b11 !
b11 +
1.
10
b11 %
b11 *
b11 '
#80
0.
03
b100 !
b100 +
18
00
05
1:
b100 %
b100 *
b100 '
#100
b101 !
b101 +
1.
10
b101 %
b101 *
b101 '
#120
0.
b110 !
b110 +
13
00
15
b110 %
b110 *
b110 '
#140
b111 !
b111 +
1.
10
b111 %
b111 *
b111 '
#160
0.
03
08
b1000 !
b1000 +
1=
00
05
0:
1?
b1000 %
b1000 *
b1000 '
#180
b1001 !
b1001 +
1.
10
b1001 %
b1001 *
b1001 '
#200
0.
b1010 !
b1010 +
13
00
15
b1010 %
b1010 *
b1010 '
#220
b1011 !
b1011 +
1.
10
b1011 %
b1011 *
b1011 '
#240
0.
03
b1100 !
b1100 +
18
00
05
1:
b1100 %
b1100 *
b1100 '
#260
b1101 !
b1101 +
1.
10
b1101 %
b1101 *
b1101 '
#280
0.
b1110 !
b1110 +
13
00
15
b1110 %
b1110 *
b1110 '
#300
b1111 !
b1111 +
1.
10
b1111 %
b1111 *
b1111 '
#320
01
03
08
0=
b0 "
b0 ,
0-
b1 !
b1 +
1.
00
05
0:
0?
1/
b0 %
b0 *
b1 $
b1 )
b1 &
b0 '
#340
13
11
b1 "
b1 ,
1-
b10 !
b10 +
0.
10
b1 %
b1 *
b1 '
#360
01
08
0-
06
1.
b0 "
b0 ,
02
b11 !
b11 +
13
00
15
b10 %
b10 *
b10 '
#380
18
16
12
03
11
b11 "
b11 ,
1-
b100 !
b100 +
0.
10
b11 %
b11 *
b11 '
#400
01
0=
0-
06
0;
1.
02
03
b0 "
b0 ,
07
b101 !
b101 +
18
00
05
1:
b100 %
b100 *
b100 '
#420
13
11
b1 "
b1 ,
1-
b110 !
b110 +
0.
10
b101 %
b101 *
b101 '
#440
0=
0;
07
01
18
0-
06
1.
b0 "
b0 ,
02
b111 !
b111 +
13
00
15
b110 %
b110 *
b110 '
#460
1=
1;
17
08
16
12
03
11
b111 "
b111 ,
1-
b1000 !
b1000 +
0.
10
b111 %
b111 *
b111 '
#480
01
0-
06
0;
1.
02
03
07
08
b0 "
b0 ,
0<
b1001 !
b1001 +
1=
00
05
0:
1?
b1000 %
b1000 *
b1000 '
#500
13
11
b1 "
b1 ,
1-
b1010 !
b1010 +
0.
10
b1001 %
b1001 *
b1001 '
#520
01
08
0-
06
1.
b0 "
b0 ,
02
b1011 !
b1011 +
13
00
15
b1010 %
b1010 *
b1010 '
#540
18
16
12
03
11
b11 "
b11 ,
1-
b1100 !
b1100 +
0.
10
b1011 %
b1011 *
b1011 '
#560
0<
01
1=
0-
06
0;
1.
02
03
b0 "
b0 ,
07
b1101 !
b1101 +
18
00
05
1:
b1100 %
b1100 *
b1100 '
#580
13
11
b1 "
b1 ,
1-
b1110 !
b1110 +
0.
10
b1101 %
b1101 *
b1101 '
#600
0<
1=
0;
07
01
18
0-
06
1.
b0 "
b0 ,
02
b1111 !
b1111 +
13
00
15
b1110 %
b1110 *
b1110 '
#620
1<
0=
1;
17
08
16
12
03
11
b1111 "
b1111 ,
1-
b0 !
b0 +
0.
10
b1111 %
b1111 *
b1111 '
#640
06
02
0;
01
07
08
0<
0=
b0 "
b0 ,
0-
0.
b10 !
b10 +
13
00
05
0:
0?
0/
14
b0 %
b0 *
b10 $
b10 )
b10 &
b0 '
#660
b11 !
b11 +
1.
10
b1 %
b1 *
b1 '
#680
18
16
b10 "
b10 ,
12
0.
b100 !
b100 +
03
00
15
b10 %
b10 *
b10 '
#700
b101 !
b101 +
1.
10
b11 %
b11 *
b11 '
#720
06
0=
02
0;
0.
13
b0 "
b0 ,
07
b110 !
b110 +
18
00
05
1:
b100 %
b100 *
b100 '
#740
b111 !
b111 +
1.
10
b101 %
b101 *
b101 '
#760
1=
1;
17
08
16
b110 "
b110 ,
12
0.
b1000 !
b1000 +
03
00
15
b110 %
b110 *
b110 '
#780
b1001 !
b1001 +
1.
10
b111 %
b111 *
b111 '
#800
06
02
0;
0.
13
07
08
b0 "
b0 ,
0<
b1010 !
b1010 +
1=
00
05
0:
1?
b1000 %
b1000 *
b1000 '
#820
b1011 !
b1011 +
1.
10
b1001 %
b1001 *
b1001 '
#840
18
16
b10 "
b10 ,
12
0.
b1100 !
b1100 +
03
00
15
b1010 %
b1010 *
b1010 '
#860
b1101 !
b1101 +
1.
10
b1011 %
b1011 *
b1011 '
#880
0<
06
1=
02
0;
0.
13
b0 "
b0 ,
07
b1110 !
b1110 +
18
00
05
1:
b1100 %
b1100 *
b1100 '
#900
b1111 !
b1111 +
1.
10
b1101 %
b1101 *
b1101 '
#920
1<
0=
1;
17
08
16
b1110 "
b1110 ,
12
0.
b0 !
b0 +
03
00
15
b1110 %
b1110 *
b1110 '
#940
b1 !
b1 +
1.
10
b1111 %
b1111 *
b1111 '
#960
06
02
0;
01
13
07
08
0<
0=
b0 "
b0 ,
0-
b11 !
b11 +
1.
00
05
0:
0?
1/
b0 %
b0 *
b11 $
b11 )
b11 &
b0 '
#980
18
16
12
03
11
b11 "
b11 ,
1-
b100 !
b100 +
0.
10
b1 %
b1 *
b1 '
#1000
01
b10 "
b10 ,
0-
1.
b101 !
b101 +
03
00
15
b10 %
b10 *
b10 '
#1020
13
11
b11 "
b11 ,
1-
b110 !
b110 +
0.
10
b11 %
b11 *
b11 '
#1040
06
02
01
0=
0-
0;
1.
13
b0 "
b0 ,
07
b111 !
b111 +
18
00
05
1:
b100 %
b100 *
b100 '
#1060
1=
1;
17
08
16
12
03
11
b111 "
b111 ,
1-
b1000 !
b1000 +
0.
10
b101 %
b101 *
b101 '
#1080
01
b110 "
b110 ,
0-
1.
b1001 !
b1001 +
03
00
15
b110 %
b110 *
b110 '
#1100
13
11
b111 "
b111 ,
1-
b1010 !
b1010 +
0.
10
b111 %
b111 *
b111 '
#1120
06
02
01
0-
0;
1.
13
07
08
b0 "
b0 ,
0<
b1011 !
b1011 +
1=
00
05
0:
1?
b1000 %
b1000 *
b1000 '
#1140
18
16
12
03
11
b11 "
b11 ,
1-
b1100 !
b1100 +
0.
10
b1001 %
b1001 *
b1001 '
#1160
01
b10 "
b10 ,
0-
1.
b1101 !
b1101 +
03
00
15
b1010 %
b1010 *
b1010 '
#1180
13
11
b11 "
b11 ,
1-
b1110 !
b1110 +
0.
10
b1011 %
b1011 *
b1011 '
#1200
06
02
0<
01
1=
0-
0;
1.
13
b0 "
b0 ,
07
b1111 !
b1111 +
18
00
05
1:
b1100 %
b1100 *
b1100 '
#1220
1<
0=
1;
17
08
16
12
03
11
b1111 "
b1111 ,
1-
b0 !
b0 +
0.
10
b1101 %
b1101 *
b1101 '
#1240
01
b1110 "
b1110 ,
0-
1.
b1 !
b1 +
03
00
15
b1110 %
b1110 *
b1110 '
#1260
13
11
b1111 "
b1111 ,
1-
b10 !
b10 +
0.
10
b1111 %
b1111 *
b1111 '
#1280
0;
07
01
06
0<
0=
0-
b0 "
b0 ,
02
0.
03
b100 !
b100 +
18
00
05
0:
0?
0/
04
19
b0 %
b0 *
b100 $
b100 )
b100 &
b0 '
#1300
b101 !
b101 +
1.
10
b1 %
b1 *
b1 '
#1320
0.
b110 !
b110 +
13
00
15
b10 %
b10 *
b10 '
#1340
b111 !
b111 +
1.
10
b11 %
b11 *
b11 '
#1360
1=
1;
b100 "
b100 ,
17
0.
03
b1000 !
b1000 +
08
00
05
1:
b100 %
b100 *
b100 '
#1380
b1001 !
b1001 +
1.
10
b101 %
b101 *
b101 '
#1400
0.
b1010 !
b1010 +
13
00
15
b110 %
b110 *
b110 '
#1420
b1011 !
b1011 +
1.
10
b111 %
b111 *
b111 '
#1440
0;
07
0.
03
18
b0 "
b0 ,
0<
b1100 !
b1100 +
1=
00
05
0:
1?
b1000 %
b1000 *
b1000 '
#1460
b1101 !
b1101 +
1.
10
b1001 %
b1001 *
b1001 '
#1480
0.
b1110 !
b1110 +
13
00
15
b1010 %
b1010 *
b1010 '
#1500
b1111 !
b1111 +
1.
10
b1011 %
b1011 *
b1011 '
#1520
1<
0=
1;
b1100 "
b1100 ,
17
0.
03
b0 !
b0 +
08
00
05
1:
b1100 %
b1100 *
b1100 '
#1540
b1 !
b1 +
1.
10
b1101 %
b1101 *
b1101 '
#1560
0.
b10 !
b10 +
13
00
15
b1110 %
b1110 *
b1110 '
#1580
b11 !
b11 +
1.
10
b1111 %
b1111 *
b1111 '
#1600
0;
07
01
03
18
0<
0=
b0 "
b0 ,
0-
b101 !
b101 +
1.
00
05
0:
0?
1/
b0 %
b0 *
b101 $
b101 )
b101 &
b0 '
#1620
13
11
b1 "
b1 ,
1-
b110 !
b110 +
0.
10
b1 %
b1 *
b1 '
#1640
0=
0;
07
01
18
0-
06
1.
b0 "
b0 ,
02
b111 !
b111 +
13
00
15
b10 %
b10 *
b10 '
#1660
1=
1;
17
08
16
12
03
11
b111 "
b111 ,
1-
b1000 !
b1000 +
0.
10
b11 %
b11 *
b11 '
#1680
01
0-
06
1.
b100 "
b100 ,
02
03
b1001 !
b1001 +
08
00
05
1:
b100 %
b100 *
b100 '
#1700
13
11
b101 "
b101 ,
1-
b1010 !
b1010 +
0.
10
b101 %
b101 *
b101 '
#1720
01
08
0-
06
1.
b100 "
b100 ,
02
b1011 !
b1011 +
13
00
15
b110 %
b110 *
b110 '
#1740
18
16
12
03
11
b111 "
b111 ,
1-
b1100 !
b1100 +
0.
10
b111 %
b111 *
b111 '
#1760
0;
07
01
0-
06
1.
02
03
18
b0 "
b0 ,
0<
b1101 !
b1101 +
1=
00
05
0:
1?
b1000 %
b1000 *
b1000 '
#1780
13
11
b1 "
b1 ,
1-
b1110 !
b1110 +
0.
10
b1001 %
b1001 *
b1001 '
#1800
0<
1=
0;
07
01
18
0-
06
1.
b0 "
b0 ,
02
b1111 !
b1111 +
13
00
15
b1010 %
b1010 *
b1010 '
#1820
1<
0=
1;
17
08
16
12
03
11
b1111 "
b1111 ,
1-
b0 !
b0 +
0.
10
b1011 %
b1011 *
b1011 '
#1840
01
0-
06
1.
b1100 "
b1100 ,
02
03
b1 !
b1 +
08
00
05
1:
b1100 %
b1100 *
b1100 '
#1860
13
11
b1101 "
b1101 ,
1-
b10 !
b10 +
0.
10
b1101 %
b1101 *
b1101 '
#1880
01
08
0-
06
1.
b1100 "
b1100 ,
02
b11 !
b11 +
13
00
15
b1110 %
b1110 *
b1110 '
#1900
18
16
12
03
11
b1111 "
b1111 ,
1-
b100 !
b100 +
0.
10
b1111 %
b1111 *
b1111 '
#1920
0;
07
06
02
01
18
0<
0=
b0 "
b0 ,
0-
0.
b110 !
b110 +
13
00
05
0:
0?
0/
14
b0 %
b0 *
b110 $
b110 )
b110 &
b0 '
#1940
b111 !
b111 +
1.
10
b1 %
b1 *
b1 '
#1960
1=
1;
17
08
16
b110 "
b110 ,
12
0.
b1000 !
b1000 +
03
00
15
b10 %
b10 *
b10 '
#1980
b1001 !
b1001 +
1.
10
b11 %
b11 *
b11 '
#2000
06
b100 "
b100 ,
02
0.
13
b1010 !
b1010 +
08
00
05
1:
b100 %
b100 *
b100 '
#2020
b1011 !
b1011 +
1.
10
b101 %
b101 *
b101 '
#2040
18
16
b110 "
b110 ,
12
0.
b1100 !
b1100 +
03
00
15
b110 %
b110 *
b110 '
#2060
b1101 !
b1101 +
1.
10
b111 %
b111 *
b111 '
#2080
0;
07
06
02
0.
13
18
b0 "
b0 ,
0<
b1110 !
b1110 +
1=
00
05
0:
1?
b1000 %
b1000 *
b1000 '
#2100
b1111 !
b1111 +
1.
10
b1001 %
b1001 *
b1001 '
#2120
1<
0=
1;
17
08
16
b1110 "
b1110 ,
12
0.
b0 !
b0 +
03
00
15
b1010 %
b1010 *
b1010 '
#2140
b1 !
b1 +
1.
10
b1011 %
b1011 *
b1011 '
#2160
06
b1100 "
b1100 ,
02
0.
13
b10 !
b10 +
08
00
05
1:
b1100 %
b1100 *
b1100 '
#2180
b11 !
b11 +
1.
10
b1101 %
b1101 *
b1101 '
#2200
18
16
b1110 "
b1110 ,
12
0.
b100 !
b100 +
03
00
15
b1110 %
b1110 *
b1110 '
#2220
b101 !
b101 +
1.
10
b1111 %
b1111 *
b1111 '
#2240
0;
07
06
02
01
13
18
0<
0=
b0 "
b0 ,
0-
b111 !
b111 +
1.
00
05
0:
0?
1/
b0 %
b0 *
b111 $
b111 )
b111 &
b0 '
#2260
1=
1;
17
08
16
12
03
11
b111 "
b111 ,
1-
b1000 !
b1000 +
0.
10
b1 %
b1 *
b1 '
#2280
01
b110 "
b110 ,
0-
1.
b1001 !
b1001 +
03
00
15
b10 %
b10 *
b10 '
#2300
13
11
b111 "
b111 ,
1-
b1010 !
b1010 +
0.
10
b11 %
b11 *
b11 '
#2320
06
02
01
b100 "
b100 ,
0-
1.
13
b1011 !
b1011 +
08
00
05
1:
b100 %
b100 *
b100 '
#2340
18
16
12
03
11
b111 "
b111 ,
1-
b1100 !
b1100 +
0.
10
b101 %
b101 *
b101 '
#2360
01
b110 "
b110 ,
0-
1.
b1101 !
b1101 +
03
00
15
b110 %
b110 *
b110 '
#2380
13
11
b111 "
b111 ,
1-
b1110 !
b1110 +
0.
10
b111 %
b111 *
b111 '
#2400
0;
07
06
02
01
0-
1.
13
18
b0 "
b0 ,
0<
b1111 !
b1111 +
1=
00
05
0:
1?
b1000 %
b1000 *
b1000 '
#2420
1<
0=
1;
17
08
16
12
03
11
b1111 "
b1111 ,
1-
b0 !
b0 +
0.
10
b1001 %
b1001 *
b1001 '
#2440
01
b1110 "
b1110 ,
0-
1.
b1 !
b1 +
03
00
15
b1010 %
b1010 *
b1010 '
#2460
13
11
b1111 "
b1111 ,
1-
b10 !
b10 +
0.
10
b1011 %
b1011 *
b1011 '
#2480
06
02
01
b1100 "
b1100 ,
0-
1.
13
b11 !
b11 +
08
00
05
1:
b1100 %
b1100 *
b1100 '
#2500
18
16
12
03
11
b1111 "
b1111 ,
1-
b100 !
b100 +
0.
10
b1101 %
b1101 *
b1101 '
#2520
01
b1110 "
b1110 ,
0-
1.
b101 !
b101 +
03
00
15
b1110 %
b1110 *
b1110 '
#2540
13
11
b1111 "
b1111 ,
1-
b110 !
b110 +
0.
10
b1111 %
b1111 *
b1111 '
#2560
0<
01
06
0;
0-
02
b0 "
b0 ,
07
0.
03
08
b1000 !
b1000 +
1=
00
05
0:
0?
0/
04
09
1>
b0 %
b0 *
b1000 $
b1000 )
b1000 &
b0 '
#2580
b1001 !
b1001 +
1.
10
b1 %
b1 *
b1 '
#2600
0.
b1010 !
b1010 +
13
00
15
b10 %
b10 *
b10 '
#2620
b1011 !
b1011 +
1.
10
b11 %
b11 *
b11 '
#2640
0.
03
b1100 !
b1100 +
18
00
05
1:
b100 %
b100 *
b100 '
#2660
b1101 !
b1101 +
1.
10
b101 %
b101 *
b101 '
#2680
0.
b1110 !
b1110 +
13
00
15
b110 %
b110 *
b110 '
#2700
b1111 !
b1111 +
1.
10
b111 %
b111 *
b111 '
#2720
b1000 "
b1000 ,
1<
0.
03
08
b0 !
b0 +
0=
00
05
0:
1?
b1000 %
b1000 *
b1000 '
#2740
b1 !
b1 +
1.
10
b1001 %
b1001 *
b1001 '
#2760
0.
b10 !
b10 +
13
00
15
b1010 %
b1010 *
b1010 '
#2780
b11 !
b11 +
1.
10
b1011 %
b1011 *
b1011 '
#2800
0.
03
b100 !
b100 +
18
00
05
1:
b1100 %
b1100 *
b1100 '
#2820
b101 !
b101 +
1.
10
b1101 %
b1101 *
b1101 '
#2840
0.
b110 !
b110 +
13
00
15
b1110 %
b1110 *
b1110 '
#2860
b111 !
b111 +
1.
10
b1111 %
b1111 *
b1111 '
#2880
0<
01
03
08
1=
b0 "
b0 ,
0-
b1001 !
b1001 +
1.
00
05
0:
0?
1/
b0 %
b0 *
b1001 $
b1001 )
b1001 &
b0 '
#2900
13
11
b1 "
b1 ,
1-
b1010 !
b1010 +
0.
10
b1 %
b1 *
b1 '
#2920
01
08
0-
06
1.
b0 "
b0 ,
02
b1011 !
b1011 +
13
00
15
b10 %
b10 *
b10 '
#2940
18
16
12
03
11
b11 "
b11 ,
1-
b1100 !
b1100 +
0.
10
b11 %
b11 *
b11 '
#2960
0<
01
1=
0-
06
0;
1.
02
03
b0 "
b0 ,
07
b1101 !
b1101 +
18
00
05
1:
b100 %
b100 *
b100 '
#2980
13
11
b1 "
b1 ,
1-
b1110 !
b1110 +
0.
10
b101 %
b101 *
b101 '
#3000
0<
1=
0;
07
01
18
0-
06
1.
b0 "
b0 ,
02
b1111 !
b1111 +
13
00
15
b110 %
b110 *
b110 '
#3020
1<
0=
1;
17
08
16
12
03
11
b1111 "
b1111 ,
1-
b0 !
b0 +
0.
10
b111 %
b111 *
b111 '
#3040
01
0-
06
0;
1.
02
03
b1000 "
b1000 ,
07
08
b1 !
b1 +
0=
00
05
0:
1?
b1000 %
b1000 *
b1000 '
#3060
13
11
b1001 "
b1001 ,
1-
b10 !
b10 +
0.
10
b1001 %
b1001 *
b1001 '
#3080
01
08
0-
06
1.
b1000 "
b1000 ,
02
b11 !
b11 +
13
00
15
b1010 %
b1010 *
b1010 '
#3100
18
16
12
03
11
b1011 "
b1011 ,
1-
b100 !
b100 +
0.
10
b1011 %
b1011 *
b1011 '
#3120
01
0=
0-
06
0;
1.
02
03
b1000 "
b1000 ,
07
b101 !
b101 +
18
00
05
1:
b1100 %
b1100 *
b1100 '
#3140
13
11
b1001 "
b1001 ,
1-
b110 !
b110 +
0.
10
b1101 %
b1101 *
b1101 '
#3160
0=
0;
07
01
18
0-
06
1.
b1000 "
b1000 ,
02
b111 !
b111 +
13
00
15
b1110 %
b1110 *
b1110 '
#3180
1=
1;
17
08
16
12
03
11
b1111 "
b1111 ,
1-
b1000 !
b1000 +
0.
10
b1111 %
b1111 *
b1111 '
#3200
06
0<
02
0;
01
07
08
1=
b0 "
b0 ,
0-
0.
b1010 !
b1010 +
13
00
05
0:
0?
0/
14
b0 %
b0 *
b1010 $
b1010 )
b1010 &
b0 '
#3220
b1011 !
b1011 +
1.
10
b1 %
b1 *
b1 '
#3240
18
16
b10 "
b10 ,
12
0.
b1100 !
b1100 +
03
00
15
b10 %
b10 *
b10 '
#3260
b1101 !
b1101 +
1.
10
b11 %
b11 *
b11 '
#3280
0<
06
1=
02
0;
0.
13
b0 "
b0 ,
07
b1110 !
b1110 +
18
00
05
1:
b100 %
b100 *
b100 '
#3300
b1111 !
b1111 +
1.
10
b101 %
b101 *
b101 '
#3320
1<
0=
1;
17
08
16
b1110 "
b1110 ,
12
0.
b0 !
b0 +
03
00
15
b110 %
b110 *
b110 '
#3340
b1 !
b1 +
1.
10
b111 %
b111 *
b111 '
#3360
06
02
0;
0.
13
b1000 "
b1000 ,
07
08
b10 !
b10 +
0=
00
05
0:
1?
b1000 %
b1000 *
b1000 '
#3380
b11 !
b11 +
1.
10
b1001 %
b1001 *
b1001 '
#3400
18
16
b1010 "
b1010 ,
12
0.
b100 !
b100 +
03
00
15
b1010 %
b1010 *
b1010 '
#3420
b101 !
b101 +
1.
10
b1011 %
b1011 *
b1011 '
#3440
06
0=
02
0;
0.
13
b1000 "
b1000 ,
07
b110 !
b110 +
18
00
05
1:
b1100 %
b1100 *
b1100 '
#3460
b111 !
b111 +
1.
10
b1101 %
b1101 *
b1101 '
#3480
1=
1;
17
08
16
b1110 "
b1110 ,
12
0.
b1000 !
b1000 +
03
00
15
b1110 %
b1110 *
b1110 '
#3500
b1001 !
b1001 +
1.
10
b1111 %
b1111 *
b1111 '
#3520
0<
06
02
0;
01
13
07
08
1=
b0 "
b0 ,
0-
b1011 !
b1011 +
1.
00
05
0:
0?
1/
b0 %
b0 *
b1011 $
b1011 )
b1011 &
b0 '
#3540
18
16
12
03
11
b11 "
b11 ,
1-
b1100 !
b1100 +
0.
10
b1 %
b1 *
b1 '
#3560
01
b10 "
b10 ,
0-
1.
b1101 !
b1101 +
03
00
15
b10 %
b10 *
b10 '
#3580
13
11
b11 "
b11 ,
1-
b1110 !
b1110 +
0.
10
b11 %
b11 *
b11 '
#3600
06
02
0<
01
1=
0-
0;
1.
13
b0 "
b0 ,
07
b1111 !
b1111 +
18
00
05
1:
b100 %
b100 *
b100 '
#3620
1<
0=
1;
17
08
16
12
03
11
b1111 "
b1111 ,
1-
b0 !
b0 +
0.
10
b101 %
b101 *
b101 '
#3640
01
b1110 "
b1110 ,
0-
1.
b1 !
b1 +
03
00
15
b110 %
b110 *
b110 '
#3660
13
11
b1111 "
b1111 ,
1-
b10 !
b10 +
0.
10
b111 %
b111 *
b111 '
#3680
06
02
01
0-
0;
1.
13
b1000 "
b1000 ,
07
08
b11 !
b11 +
0=
00
05
0:
1?
b1000 %
b1000 *
b1000 '
#3700
18
16
12
03
11
b1011 "
b1011 ,
1-
b100 !
b100 +
0.
10
b1001 %
b1001 *
b1001 '
#3720
01
b1010 "
b1010 ,
0-
1.
b101 !
b101 +
03
00
15
b1010 %
b1010 *
b1010 '
#3740
13
11
b1011 "
b1011 ,
1-
b110 !
b110 +
0.
10
b1011 %
b1011 *
b1011 '
#3760
06
02
01
0=
0-
0;
1.
13
b1000 "
b1000 ,
07
b111 !
b111 +
18
00
05
1:
b1100 %
b1100 *
b1100 '
#3780
1=
1;
17
08
16
12
03
11
b1111 "
b1111 ,
1-
b1000 !
b1000 +
0.
10
b1101 %
b1101 *
b1101 '
#3800
01
b1110 "
b1110 ,
0-
1.
b1001 !
b1001 +
03
00
15
b1110 %
b1110 *
b1110 '
#3820
13
11
b1111 "
b1111 ,
1-
b1010 !
b1010 +
0.
10
b1111 %
b1111 *
b1111 '
#3840
0<
0;
07
01
06
1=
0-
b0 "
b0 ,
02
0.
03
b1100 !
b1100 +
18
00
05
0:
0?
0/
04
19
b0 %
b0 *
b1100 $
b1100 )
b1100 &
b0 '
#3860
b1101 !
b1101 +
1.
10
b1 %
b1 *
b1 '
#3880
0.
b1110 !
b1110 +
13
00
15
b10 %
b10 *
b10 '
#3900
b1111 !
b1111 +
1.
10
b11 %
b11 *
b11 '
#3920
1<
0=
1;
b1100 "
b1100 ,
17
0.
03
b0 !
b0 +
08
00
05
1:
b100 %
b100 *
b100 '
#3940
b1 !
b1 +
1.
10
b101 %
b101 *
b101 '
#3960
0.
b10 !
b10 +
13
00
15
b110 %
b110 *
b110 '
#3980
b11 !
b11 +
1.
10
b111 %
b111 *
b111 '
#4000
0;
b1000 "
b1000 ,
07
0.
03
18
b100 !
b100 +
0=
00
05
0:
1?
b1000 %
b1000 *
b1000 '
#4020
b101 !
b101 +
1.
10
b1001 %
b1001 *
b1001 '
#4040
0.
b110 !
b110 +
13
00
15
b1010 %
b1010 *
b1010 '
#4060
b111 !
b111 +
1.
10
b1011 %
b1011 *
b1011 '
#4080
1=
1;
b1100 "
b1100 ,
17
0.
03
b1000 !
b1000 +
08
00
05
1:
b1100 %
b1100 *
b1100 '
#4100
b1001 !
b1001 +
1.
10
b1101 %
b1101 *
b1101 '
#4120
0.
b1010 !
b1010 +
13
00
15
b1110 %
b1110 *
b1110 '
#4140
b1011 !
b1011 +
1.
10
b1111 %
b1111 *
b1111 '
#4160
0<
0;
07
01
03
18
1=
b0 "
b0 ,
0-
b1101 !
b1101 +
1.
00
05
0:
0?
1/
b0 %
b0 *
b1101 $
b1101 )
b1101 &
b0 '
#4180
13
11
b1 "
b1 ,
1-
b1110 !
b1110 +
0.
10
b1 %
b1 *
b1 '
#4200
0<
1=
0;
07
01
18
0-
06
1.
b0 "
b0 ,
02
b1111 !
b1111 +
13
00
15
b10 %
b10 *
b10 '
#4220
1<
0=
1;
17
08
16
12
03
11
b1111 "
b1111 ,
1-
b0 !
b0 +
0.
10
b11 %
b11 *
b11 '
#4240
01
0-
06
1.
b1100 "
b1100 ,
02
03
b1 !
b1 +
08
00
05
1:
b100 %
b100 *
b100 '
#4260
13
11
b1101 "
b1101 ,
1-
b10 !
b10 +
0.
10
b101 %
b101 *
b101 '
#4280
01
08
0-
06
1.
b1100 "
b1100 ,
02
b11 !
b11 +
13
00
15
b110 %
b110 *
b110 '
#4300
18
16
12
03
11
b1111 "
b1111 ,
1-
b100 !
b100 +
0.
10
b111 %
b111 *
b111 '
#4320
0;
07
01
0-
06
1.
b1000 "
b1000 ,
02
03
18
b101 !
b101 +
0=
00
05
0:
1?
b1000 %
b1000 *
b1000 '
#4340
13
11
b1001 "
b1001 ,
1-
b110 !
b110 +
0.
10
b1001 %
b1001 *
b1001 '
#4360
0=
0;
07
01
18
0-
06
1.
b1000 "
b1000 ,
02
b111 !
b111 +
13
00
15
b1010 %
b1010 *
b1010 '
#4380
1=
1;
17
08
16
12
03
11
b1111 "
b1111 ,
1-
b1000 !
b1000 +
0.
10
b1011 %
b1011 *
b1011 '
#4400
01
0-
06
1.
b1100 "
b1100 ,
02
03
b1001 !
b1001 +
08
00
05
1:
b1100 %
b1100 *
b1100 '
#4420
13
11
b1101 "
b1101 ,
1-
b1010 !
b1010 +
0.
10
b1101 %
b1101 *
b1101 '
#4440
01
08
0-
06
1.
b1100 "
b1100 ,
02
b1011 !
b1011 +
13
00
15
b1110 %
b1110 *
b1110 '
#4460
18
16
12
03
11
b1111 "
b1111 ,
1-
b1100 !
b1100 +
0.
10
b1111 %
b1111 *
b1111 '
#4480
0<
0;
07
06
02
01
18
1=
b0 "
b0 ,
0-
0.
b1110 !
b1110 +
13
00
05
0:
0?
0/
14
b0 %
b0 *
b1110 $
b1110 )
b1110 &
b0 '
#4500
b1111 !
b1111 +
1.
10
b1 %
b1 *
b1 '
#4520
1<
0=
1;
17
08
16
b1110 "
b1110 ,
12
0.
b0 !
b0 +
03
00
15
b10 %
b10 *
b10 '
#4540
b1 !
b1 +
1.
10
b11 %
b11 *
b11 '
#4560
06
b1100 "
b1100 ,
02
0.
13
b10 !
b10 +
08
00
05
1:
b100 %
b100 *
b100 '
#4580
b11 !
b11 +
1.
10
b101 %
b101 *
b101 '
#4600
18
16
b1110 "
b1110 ,
12
0.
b100 !
b100 +
03
00
15
b110 %
b110 *
b110 '
#4620
b101 !
b101 +
1.
10
b111 %
b111 *
b111 '
#4640
0;
07
06
b1000 "
b1000 ,
02
0.
13
18
b110 !
b110 +
0=
00
05
0:
1?
b1000 %
b1000 *
b1000 '
#4660
b111 !
b111 +
1.
10
b1001 %
b1001 *
b1001 '
#4680
1=
1;
17
08
16
b1110 "
b1110 ,
12
0.
b1000 !
b1000 +
03
00
15
b1010 %
b1010 *
b1010 '
#4700
b1001 !
b1001 +
1.
10
b1011 %
b1011 *
b1011 '
#4720
06
b1100 "
b1100 ,
02
0.
13
b1010 !
b1010 +
08
00
05
1:
b1100 %
b1100 *
b1100 '
#4740
b1011 !
b1011 +
1.
10
b1101 %
b1101 *
b1101 '
