LAB 4/q3/question3.v
module half_adder(a, b, sum, carry);
input a, b;
output sum, carry;

assign sum = a ^ b;
assign carry = a & b;
endmodule

module question3(A, B, P);
input [1:0] A;
input [1:0] B;
output [3:0] P;

wire pp1, pp2, pp3;
wire ha1_sum, ha1_carry;
wire ha2_sum, ha2_carry;


assign P[0] = A[0] & B[0];
assign pp1  = A[1] & B[0];
assign pp2  = A[0] & B[1];
assign pp3  = A[1] & B[1];

half_adder ha1(pp1, pp2, ha1_sum, ha1_carry);
assign P[1] = ha1_sum;
half_adder ha2(ha1_carry, pp3, P[2], P[3]);

endmodule

LAB 4/q3/question3_tb.v
`timescale 1ns/1ns
`include "question3.v"

module question3_tb();
reg [1:0] A;
reg [1:0] B;
wire [3:0] P;


integer i,j;
question3 m(A, B, P);

initial
begin
    $dumpfile("question3.vcd");
    $dumpvars(0, question3_tb);
    
    for (i = 0; i < 4; i = i + 1) begin
        for (j = 0; j < 4; j = j + 1) begin
            A = i;
            B = j;
            #20;
        end
    end
    $display("Test Complete!");
end
endmodule

LAB 4/q3/question3.vcd
$date
	Sat Aug 22 10:56:36 2026
$end
$version
	Icarus Verilog
$end
$timescale
	1ns
$end
$scope module question3_tb $end
$var wire 4 ! P [3:0] $end
$var reg 2 " A [1:0] $end
$var reg 2 # B [1:0] $end
$var integer 32 $ i [31:0] $end
$var integer 32 % j [31:0] $end
$scope module m $end
$var wire 2 & A [1:0] $end
$var wire 2 ' B [1:0] $end
$var wire 1 ( pp1 $end
$var wire 1 ) pp2 $end
$var wire 1 * pp3 $end
$var wire 1 + ha1_sum $end
$var wire 1 , ha1_carry $end
$var wire 4 - P [3:0] $end
$scope module ha1 $end
$var wire 1 ( a $end
$var wire 1 ) b $end
$var wire 1 , carry $end
$var wire 1 + sum $end
$upscope $end
$scope module ha2 $end
$var wire 1 , a $end
$var wire 1 * b $end
$var wire 1 . carry $end
$var wire 1 / sum $end
$upscope $end
$upscope $end
$upscope $end
$enddefinitions $end
#0
$dumpvars
0/
0.
b0 -
0,
0+
0*
0)
0(
b0 '
b0 &
b0 %
b0 $
b0 #
b0 "
b0 !
$end
#20
b1 #
b1 '
b1 %
#40
b10 #
b10 '
b10 %
#60
b11 #
b11 '
b11 %
#80
b0 #
b0 '
b1 "
b1 &
b1 $
b0 %
#100
b1 !
b1 -
b1 #
b1 '
b1 %
#120
1+
b10 !
b10 -
1)
b10 #
b10 '
b10 %
#140
b11 !
b11 -
b11 #
b11 '
b11 %
#160
0+
b0 !
b0 -
0)
b0 #
b0 '
b10 "
b10 &
b10 $
b0 %
#180
b10 !
b10 -
1+
1(
b1 #
b1 '
b1 %
#200
0+
b100 !
b100 -
1/
0(
1*
b10 #
b10 '
b10 %
#220
b110 !
b110 -
1+
1(
b11 #
b11 '
b11 %
#240
0+
b0 !
b0 -
0/
0(
0*
b0 #
b0 '
b11 "
b11 &
b11 $
b0 %
#260
1+
b11 !
b11 -
1(
b1 #
b1 '
b1 %
#280
1/
b110 !
b110 -
0(
1)
1*
b10 #
b10 '
b10 %
#300
0/
1.
0+
1,
b1001 !
b1001 -
1(
b11 #
b11 '
b11 %
#320
b100 $
b100 %
