LAB 3/q4/question4.v
module question4(a,b,c,d,f);

input a,b,c,d;
output f;

nand(ab,a,a);
nand(bb, b, b);
nand(db, d, d);

nand(p, c, d);
nand(q, bb, db);
nand(r, ab, bb);

nand(f, p, q, r);


endmodule

LAB 3/q4/question4_tb.v
`timescale 1ns/1ns
`include "question4.v"

module question4_tb();

reg a,b,c,d;
wire f;

question4 q4(a,b,c,d,f);


initial
begin

	$dumpfile("question4_tb.vcd");
	$dumpvars(0, question4_tb);
	
	a = 1'b0;b=1'b0;c=1'b0;d=1'b0;
	#20
	
	a = 1'b0;b=1'b0;c=1'b0;d=1'b1;
	#20
	
	a = 1'b0;b=1'b0;c=1'b1;d=1'b0;
	#20
	
	a = 1'b0;b=1'b0;c=1'b1;d=1'b1;
	#20
	
	a = 1'b0;b=1'b1;c=1'b0;d=1'b0;
	#20
	
	a = 1'b0;b=1'b1;c=1'b0;d=1'b1;
	#20
	
	a = 1'b0;b=1'b1;c=1'b1;d=1'b0;
	#20
	
	a = 1'b0;b=1'b1;c=1'b1;d=1'b1;
	#20
	
	a = 1'b1;b=1'b0;c=1'b0;d=1'b0;
	#20
	
	a = 1'b1;b=1'b0;c=1'b0;d=1'b1;
	#20
	
	a = 1'b1;b=1'b0;c=1'b1;d=1'b0;
	#20
	
	a = 1'b1;b=1'b0;c=1'b1;d=1'b1;
	#20
	
	a = 1'b1;b=1'b1;c=1'b0;d=1'b0;
	#20
	
	a = 1'b1;b=1'b1;c=1'b0;d=1'b1;
	#20
	
	a = 1'b1;b=1'b1;c=1'b1;d=1'b0;
	#20
	
	a = 1'b1;b=1'b1;c=1'b1;d=1'b1;
	#20
	
	$display("Test complete");
	
end
endmodule

LAB 3/q4/question4_tb.vcd
$date
	Sat Aug  8 10:04:10 2026
$end
$version
	Icarus Verilog
$end
$timescale
	1ns
$end
$scope module question4_tb $end
$var wire 1 ! f $end
$var reg 1 " a $end
$var reg 1 # b $end
$var reg 1 $ c $end
$var reg 1 % d $end
$scope module q4 $end
$var wire 1 " a $end
$var wire 1 & ab $end
$var wire 1 # b $end
$var wire 1 ' bb $end
$var wire 1 $ c $end
$var wire 1 % d $end
$var wire 1 ( db $end
$var wire 1 ! f $end
$var wire 1 ) p $end
$var wire 1 * q $end
$var wire 1 + r $end
$upscope $end
$upscope $end
$enddefinitions $end
#0
$dumpvars
0+
0*
1)
1(
1'
1&
0%
0$
0#
0"
1!
$end
#20
1*
0(
1%
#40
0*
1(
0%
1$
#60
1*
0(
0)
1%
#80
0!
1+
1(
1)
0'
0%
0$
1#
#100
0(
1%
#120
1(
0%
1$
#140
1!
0(
0)
1%
#160
0*
1(
1)
1'
0&
0%
0$
0#
1"
#180
0!
1*
0(
1%
#200
1!
0*
1(
0%
1$
#220
1*
0(
0)
1%
#240
0!
1(
1)
0'
0%
0$
1#
#260
0(
1%
#280
1(
0%
1$
#300
1!
0(
0)
1%
