LAB 8/Q3/question3.v
module question3(CLK, reset, Q);
input CLK;
input reset;
output reg [4:0] Q;

always @(posedge CLK or posedge reset) begin
    if (reset)
        Q <= 5'b00000;
    else begin
        Q <= {Q[3:0], ~Q[4]};
    end
end
endmodule

LAB 8/Q3/question3_tb.v
`include "question3.v"
`timescale 1ns/1ns

module question3_tb();
reg CLK;
reg reset;
wire [4:0] Q;

question3 q3(CLK, reset, Q);
initial begin
CLK = 0;
forever #20 CLK = ~CLK;
end
initial begin
#200; $finish;
end
initial begin
	$dumpfile("question3.vcd");
	$dumpvars(0, question3_tb);
	reset = 1; 
        #45;reset = 0; 
        #100;
        reset = 1; 
        #20;
        reset = 0;
        #35;
	$display("Test Complete!");
end
endmodule

LAB 8/Q3/question3.vcd
$date
	Sat Oct  3 10:17:22 2026
$end
$version
	Icarus Verilog
$end
$timescale
	1ns
$end
$scope module question3_tb $end
$var wire 5 ! Q [4:0] $end
$var reg 1 " CLK $end
$var reg 1 # reset $end
$scope module q3 $end
$var wire 1 " CLK $end
$var wire 1 # reset $end
$var reg 5 $ Q [4:0] $end
$upscope $end
$upscope $end
$enddefinitions $end
#0
$dumpvars
b0 $
1#
0"
b0 !
$end
#20
1"
#40
0"
#45
0#
#60
b1 !
b1 $
1"
#80
0"
#100
b11 !
b11 $
1"
#120
0"
#140
b111 !
b111 $
1"
#145
b0 !
b0 $
1#
#160
0"
#165
0#
#180
b1 !
b1 $
1"
