LAB 0/FullAdder/fullAdder.v
module fullAdder(a, b, cin, s, cout);
input a, b, cin;
output s, cout;

assign s = a^b^cin;
assign cout = a*b + b*cin + a*cin; 

endmodule

LAB 0/FullAdder/fullAdder_tb.v
`timescale 1ns/1ns
`include "fullAdder.v"

module fullAdder_tb();
reg a, b, cin;
wire s, cout;

fullAdder fa(a, b, cin, s, cout);
initial
begin

	$dumpfile("fullAdder_tb.vcd");
	$dumpvars(0, fullAdder_tb);
	
	a=1'b0;b=1'b0;cin=1'b0;
	#20;
	
	a=1'b0;b=1'b0;cin=1'b1;
	#20;
	
	a=1'b0;b=1'b1;cin=1'b0;
	#20;
	
	a=1'b0;b=1'b1;cin=1'b1;
	#20;
	
	a=1'b1;b=1'b0;cin=1'b0;
	#20;
	
	a=1'b1;b=1'b0;cin=1'b1;
	#20;
	
	a=1'b1;b=1'b1;cin=1'b0;
	#20;
	
	a=1'b1;b=1'b1;cin=1'b1;
	#20;
	
end
endmodule

LAB 0/FullAdder/fullAdder_tb.vcd
$date
	Sat Jul 25 10:09:05 2026
$end
$version
	Icarus Verilog
$end
$timescale
	1ns
$end
$scope module fullAdder_tb $end
$var wire 1 ! s $end
$var wire 1 " cout $end
$var reg 1 # a $end
$var reg 1 $ b $end
$var reg 1 % cin $end
$scope module fa $end
$var wire 1 # a $end
$var wire 1 $ b $end
$var wire 1 % cin $end
$var wire 1 ! s $end
$var wire 1 " cout $end
$upscope $end
$upscope $end
$enddefinitions $end
#0
$dumpvars
0%
0$
0#
0"
0!
$end
#20
1!
1%
#40
0%
0"
1$
#60
0!
1"
1%
#80
1!
0%
0$
0"
1#
#100
0!
1"
1%
#120
0%
1"
1$
#140
1!
1"
1%
