LAB 3/q2/question2.v
module question2(a,b,c,d,f);

input a,b,c,d;
output f;

nor(p, b, d);
nor(q, b, c);

nor(r, p, q);
nor(f, r, r);


endmodule

LAB 3/q2/question2_tb.v
`timescale 1ns/1ns
`include "question2.v"

module question2_tb();

reg a, b, c, d;
wire f;

question2 q2(a,b,c,d,f);


initial
begin

	$dumpfile("question2_tb.vcd");
	$dumpvars(0, question2_tb);
	
	a = 1'b0;b=1'b0;c=1'b0;d=1'b0;
	#20
	
	a = 1'b0;b=1'b0;c=1'b0;d=1'b1;
	#20
	
	a = 1'b0;b=1'b0;c=1'b1;d=1'b0;
	#20
	
	a = 1'b0;b=1'b0;c=1'b1;d=1'b1;
	#20
	
	a = 1'b0;b=1'b1;c=1'b0;d=1'b0;
	#20
	
	a = 1'b0;b=1'b1;c=1'b0;d=1'b1;
	#20
	
	a = 1'b0;b=1'b1;c=1'b1;d=1'b0;
	#20
	
	a = 1'b0;b=1'b1;c=1'b1;d=1'b1;
	#20
	
	a = 1'b1;b=1'b0;c=1'b0;d=1'b0;
	#20
	
	a = 1'b1;b=1'b0;c=1'b0;d=1'b1;
	#20
	
	a = 1'b1;b=1'b0;c=1'b1;d=1'b0;
	#20
	
	a = 1'b1;b=1'b0;c=1'b1;d=1'b1;
	#20
	
	a = 1'b1;b=1'b1;c=1'b0;d=1'b0;
	#20
	
	a = 1'b1;b=1'b1;c=1'b0;d=1'b1;
	#20
	
	a = 1'b1;b=1'b1;c=1'b1;d=1'b0;
	#20
	
	a = 1'b1;b=1'b1;c=1'b1;d=1'b1;
	#20
	
	$display("Test complete");
	
end
endmodule

LAB 3/q2/question2_tb.vcd
$date
	Sat Aug  8 09:34:03 2026
$end
$version
	Icarus Verilog
$end
$timescale
	1ns
$end
$scope module question2_tb $end
$var wire 1 ! f $end
$var reg 1 " a $end
$var reg 1 # b $end
$var reg 1 $ c $end
$var reg 1 % d $end
$scope module q2 $end
$var wire 1 " a $end
$var wire 1 # b $end
$var wire 1 $ c $end
$var wire 1 % d $end
$var wire 1 ! f $end
$var wire 1 & p $end
$var wire 1 ' q $end
$var wire 1 ( r $end
$upscope $end
$upscope $end
$enddefinitions $end
#0
$dumpvars
0(
1'
1&
0%
0$
0#
0"
1!
$end
#20
0&
1%
#40
1&
0'
0%
1$
#60
0!
1(
0&
1%
#80
0%
0$
1#
#100
1%
#120
0%
1$
#140
1%
#160
1!
0(
1&
1'
0%
0$
0#
1"
#180
0&
1%
#200
1&
0'
0%
1$
#220
0!
1(
0&
1%
#240
0%
0$
1#
#260
1%
#280
0%
1$
#300
1%
