LAB 7/Q1/question1.v
module question1;
    reg clk = 0;
    reg reset = 0;
    reg d = 0;
    reg q = 0;

    always @(posedge clk or posedge reset) begin
        if (reset)
            q <= 1'b0;
        else
            q <= d;
    end

endmodule

LAB 7/Q1/question1_tb.v
`include "question1.v"
`timescale 1ns/1ns

module question1_tb();

question1 q1();

initial
begin
    $dumpfile("question1.vcd");
    $dumpvars(0, question1_tb);

    #10 q1.reset = 1; q1.d = 0;
    #15 q1.reset = 0;
    #10 q1.d = 1;
    #15 q1.d = 0;
    #10 q1.d = 1;
    #20;
    
    $display("Test Complete");
    $finish;
end

always #5 q1.clk = ~q1.clk;

endmodule

LAB 7/Q1/question1.vcd
$date
	Sat Sep 12 09:30:55 2026
$end
$version
	Icarus Verilog
$end
$timescale
	1ns
$end
$scope module question1_tb $end
$scope module q1 $end
$var reg 1 ! clk $end
$var reg 1 " d $end
$var reg 1 # q $end
$var reg 1 $ reset $end
$upscope $end
$upscope $end
$enddefinitions $end
#0
$dumpvars
0$
0#
0"
0!
$end
#5
1!
#10
0!
1$
#15
1!
#20
0!
#25
1!
0$
#30
0!
#35
1#
1!
1"
#40
0!
#45
1!
#50
0!
0"
#55
0#
1!
#60
0!
1"
#65
1#
1!
