LAB 1/q1/question1b.v
module question1b(a,b,c,d,f);
input a,b,c,d;
output f;

assign f = d | (~a & ~c & d) | (~b & ~c & d);

endmodule

LAB 1/q1/question1b_tb.v
`timescale 1ns/1ns
`include "question1b.v"

module question1b_tb();

reg a, b, c, d;
wire f;

question1b q1(a, b, c, d, f);
initial
begin

	$dumpfile("question1b_tb.vcd");
	$dumpvars(0, question1b_tb);
	
	a = 1'b0;b=1'b0;c=1'b0;d=1'b0;
	#20
	
	a = 1'b0;b=1'b0;c=1'b0;d=1'b1;
	#20
	
	a = 1'b0;b=1'b0;c=1'b1;d=1'b0;
	#20
	
	a = 1'b0;b=1'b0;c=1'b1;d=1'b1;
	#20
	
	a = 1'b0;b=1'b1;c=1'b0;d=1'b0;
	#20
	
	a = 1'b0;b=1'b1;c=1'b0;d=1'b1;
	#20
	
	a = 1'b0;b=1'b1;c=1'b1;d=1'b0;
	#20
	
	a = 1'b0;b=1'b1;c=1'b1;d=1'b1;
	#20
	
	a = 1'b1;b=1'b0;c=1'b0;d=1'b0;
	#20
	
	a = 1'b1;b=1'b0;c=1'b0;d=1'b1;
	#20
	
	a = 1'b1;b=1'b0;c=1'b1;d=1'b0;
	#20
	
	a = 1'b1;b=1'b0;c=1'b1;d=1'b1;
	#20
	
	a = 1'b1;b=1'b1;c=1'b0;d=1'b0;
	#20
	
	a = 1'b1;b=1'b1;c=1'b0;d=1'b1;
	#20
	
	a = 1'b1;b=1'b1;c=1'b1;d=1'b0;
	#20
	
	a = 1'b1;b=1'b1;c=1'b1;d=1'b1;
	#20
	
	$display("Test complete");
end
endmodule

LAB 1/q1/question1b_tb.vcd
$date
	Sat Aug  1 10:51:51 2026
$end
$version
	Icarus Verilog
$end
$timescale
	1ns
$end
$scope module question1b_tb $end
$var wire 1 ! f $end
$var reg 1 " a $end
$var reg 1 # b $end
$var reg 1 $ c $end
$var reg 1 % d $end
$scope module q1 $end
$var wire 1 " a $end
$var wire 1 # b $end
$var wire 1 $ c $end
$var wire 1 % d $end
$var wire 1 ! f $end
$upscope $end
$upscope $end
$enddefinitions $end
#0
$dumpvars
0%
0$
0#
0"
0!
$end
#20
1!
1%
#40
0!
0%
1$
#60
1!
1%
#80
0!
0%
0$
1#
#100
1!
1%
#120
0!
0%
1$
#140
1!
1%
#160
0!
0%
0$
0#
1"
#180
1!
1%
#200
0!
0%
1$
#220
1!
1%
#240
0!
0%
0$
1#
#260
1!
1%
#280
0!
0%
1$
#300
1!
1%
