LAB 9/Q1/question1.v
module question1(E, x, CLK, Q);
    input E, x, CLK;
    output [1:0] Q;

    wire JA, KA, JB, KB;
    wire A, B;

    assign JA = E ? (x ? B : ~B) : 1'b0;
    assign KA = E ? (x ? B : ~B) : 1'b0;
    assign JB = E;
    assign KB = E;

    jk_ff ff_a(JA, KA, CLK, A);
    jk_ff ff_b(JB, KB, CLK, B);

    assign Q = {A, B};

endmodule

module jk_ff(J, K, CLK, Q);
    input J, K, CLK;
    output reg Q;

    initial Q = 1'b0;

    always @(posedge CLK) begin
        case ({J, K})
            2'b00: Q <= Q;
            2'b01: Q <= 1'b0;
            2'b10: Q <= 1'b1;
            2'b11: Q <= ~Q;
        endcase
    end
endmodule

LAB 9/Q1/question1_tb.v
`include "question1.v"
`timescale 1ns/1ns

module question1_tb();
    reg CLK;
    reg E;
    reg x;
    wire [1:0] Q;

    question1 q1(E, x, CLK, Q);

    initial begin
        CLK = 0;
        forever #20 CLK = ~CLK;
    end

    initial begin
        #300; 
        $finish;
    end

    initial begin
        $dumpfile("question1.vcd");
        $dumpvars(0, question1_tb);
        
        E = 0; x = 0; #40;
        
        E = 1; x = 1; #100; 
        
        E = 1; x = 0; #100; 
        
        E = 0; x = 1; #40;
        
        $display("Test Complete!");
    end

endmodule

LAB 9/Q1/question1.vcd
$date
	Sat Oct 10 09:13:30 2026
$end
$version
	Icarus Verilog
$end
$timescale
	1ns
$end
$scope module question1_tb $end
$var wire 2 ! Q [1:0] $end
$var reg 1 " CLK $end
$var reg 1 # E $end
$var reg 1 $ x $end
$scope module q1 $end
$var wire 1 " CLK $end
$var wire 1 # E $end
$var wire 1 % JB $end
$var wire 1 & KB $end
$var wire 1 $ x $end
$var wire 2 ' Q [1:0] $end
$var wire 1 ( KA $end
$var wire 1 ) JA $end
$var wire 1 * B $end
$var wire 1 + A $end
$scope module ff_a $end
$var wire 1 " CLK $end
$var wire 1 ) J $end
$var wire 1 ( K $end
$var reg 1 + Q $end
$upscope $end
$scope module ff_b $end
$var wire 1 " CLK $end
$var wire 1 % J $end
$var wire 1 & K $end
$var reg 1 * Q $end
$upscope $end
$upscope $end
$upscope $end
$enddefinitions $end
#0
$dumpvars
0+
0*
0)
0(
b0 '
0&
0%
0$
0#
0"
b0 !
$end
#20
1"
#40
0)
0(
0"
1$
1%
1&
1#
#60
1(
1)
b1 !
b1 '
1*
1"
#80
0"
#100
0(
0)
1+
b10 !
b10 '
0*
1"
#120
0"
#140
b11 !
b11 '
1*
0)
0(
1"
0$
#160
0"
#180
1(
1)
b10 !
b10 '
0*
1"
#200
0"
#220
0(
0)
1*
b1 !
b1 '
0+
1"
#240
0"
1$
0%
0&
0#
