LAB 6/Q2/question2.v
module question2(W, E, Y);

input [3:0] W;
input E;
output [0:15] Y;

wire [0:15] Y1, Y2;

dec3to8 d1(W, E, Y1);
dec3to8 d2(W, ~E, Y2);

assign Y = Y1 | Y2;

endmodule


module dec3to8(W, E, Y);
input [3:0] W;
input E;
output reg [0:15] Y;
integer k;

always @(*) begin
for (k = 0; k <= 7; k = k + 1) begin
if (E) begin
Y[k]   = (W[1:0] == k);
Y[k+8] = 1'b0;
end else begin
Y[k]   = 1'b0;
Y[k+8] = (W[1:0] == k);
end
end
end
endmodule

LAB 6/Q2/question2_tb.v
`include "question2.v"
`timescale 1ns/1ns

module question1_tb();
reg [3:0]W;
reg E;
wire [0:15] Y;

integer i,j;
question2 q2(W, E, Y);
initial
begin
	$dumpfile("question2.vcd");
	$dumpvars(0, question1_tb);
	for(i=0;i<=1;i=i+1) begin
		for(j=0;j<=15;j=j+1) begin
			W=j;E=i;
			#20;
		end
	end
	$display("Test Complete");
end
endmodule

LAB 6/Q2/question2.vcd
$date
	Wed Sep  2 09:55:34 2026
$end
$version
	Icarus Verilog
$end
$timescale
	1ns
$end
$scope module question1_tb $end
$var wire 16 ! Y [0:15] $end
$var reg 1 " E $end
$var reg 4 # W [3:0] $end
$var integer 32 $ i [31:0] $end
$var integer 32 % j [31:0] $end
$scope module q2 $end
$var wire 1 " E $end
$var wire 4 & W [3:0] $end
$var wire 16 ' Y [0:15] $end
$var wire 16 ( Y2 [0:15] $end
$var wire 16 ) Y1 [0:15] $end
$scope module d1 $end
$var wire 1 " E $end
$var wire 4 * W [3:0] $end
$var reg 16 + Y [0:15] $end
$var integer 32 , k [31:0] $end
$upscope $end
$scope module d2 $end
$var wire 1 - E $end
$var wire 4 . W [3:0] $end
$var reg 16 / Y [0:15] $end
$var integer 32 0 k [31:0] $end
$upscope $end
$upscope $end
$upscope $end
$enddefinitions $end
#0
$dumpvars
b1000 0
b1000000000000000 /
b0 .
1-
b1000 ,
b10000000 +
b0 *
b10000000 )
b1000000000000000 (
b1000000010000000 '
b0 &
b0 %
b0 $
b0 #
0"
b1000000010000000 !
$end
#20
b100000001000000 !
b100000001000000 '
b1000000 )
b1000000 +
b1000 ,
b100000000000000 (
b100000000000000 /
b1000 0
b1 #
b1 &
b1 *
b1 .
b1 %
#40
b10000000100000 !
b10000000100000 '
b100000 )
b100000 +
b1000 ,
b10000000000000 (
b10000000000000 /
b1000 0
b10 #
b10 &
b10 *
b10 .
b10 %
#60
b1000000010000 !
b1000000010000 '
b10000 )
b10000 +
b1000 ,
b1000000000000 (
b1000000000000 /
b1000 0
b11 #
b11 &
b11 *
b11 .
b11 %
#80
b1000000010000000 !
b1000000010000000 '
b10000000 )
b10000000 +
b1000 ,
b1000000000000000 (
b1000000000000000 /
b1000 0
b100 #
b100 &
b100 *
b100 .
b100 %
#100
b100000001000000 !
b100000001000000 '
b1000000 )
b1000000 +
b1000 ,
b100000000000000 (
b100000000000000 /
b1000 0
b101 #
b101 &
b101 *
b101 .
b101 %
#120
b10000000100000 !
b10000000100000 '
b100000 )
b100000 +
b1000 ,
b10000000000000 (
b10000000000000 /
b1000 0
b110 #
b110 &
b110 *
b110 .
b110 %
#140
b1000000010000 !
b1000000010000 '
b10000 )
b10000 +
b1000 ,
b1000000000000 (
b1000000000000 /
b1000 0
b111 #
b111 &
b111 *
b111 .
b111 %
#160
b1000000010000000 !
b1000000010000000 '
b10000000 )
b10000000 +
b1000 ,
b1000000000000000 (
b1000000000000000 /
b1000 0
b1000 #
b1000 &
b1000 *
b1000 .
b1000 %
#180
b100000001000000 !
b100000001000000 '
b1000000 )
b1000000 +
b1000 ,
b100000000000000 (
b100000000000000 /
b1000 0
b1001 #
b1001 &
b1001 *
b1001 .
b1001 %
#200
b10000000100000 !
b10000000100000 '
b100000 )
b100000 +
b1000 ,
b10000000000000 (
b10000000000000 /
b1000 0
b1010 #
b1010 &
b1010 *
b1010 .
b1010 %
#220
b1000000010000 !
b1000000010000 '
b10000 )
b10000 +
b1000 ,
b1000000000000 (
b1000000000000 /
b1000 0
b1011 #
b1011 &
b1011 *
b1011 .
b1011 %
#240
b1000000010000000 !
b1000000010000000 '
b10000000 )
b10000000 +
b1000 ,
b1000000000000000 (
b1000000000000000 /
b1000 0
b1100 #
b1100 &
b1100 *
b1100 .
b1100 %
#260
b100000001000000 !
b100000001000000 '
b1000000 )
b1000000 +
b1000 ,
b100000000000000 (
b100000000000000 /
b1000 0
b1101 #
b1101 &
b1101 *
b1101 .
b1101 %
#280
b10000000100000 !
b10000000100000 '
b100000 )
b100000 +
b1000 ,
b10000000000000 (
b10000000000000 /
b1000 0
b1110 #
b1110 &
b1110 *
b1110 .
b1110 %
#300
b1000000010000 !
b1000000010000 '
b10000 )
b10000 +
b1000 ,
b1000000000000 (
b1000000000000 /
b1000 0
b1111 #
b1111 &
b1111 *
b1111 .
b1111 %
#320
b1000000010000000 !
b1000000010000000 '
0-
b1000000000000000 )
b1000000000000000 +
b1000 ,
b10000000 (
b10000000 /
b1000 0
1"
b0 #
b0 &
b0 *
b0 .
b1 $
b0 %
#340
b100000001000000 !
b100000001000000 '
b100000000000000 )
b100000000000000 +
b1000 ,
b1000000 (
b1000000 /
b1000 0
b1 #
b1 &
b1 *
b1 .
b1 %
#360
b10000000100000 !
b10000000100000 '
b10000000000000 )
b10000000000000 +
b1000 ,
b100000 (
b100000 /
b1000 0
b10 #
b10 &
b10 *
b10 .
b10 %
#380
b1000000010000 !
b1000000010000 '
b1000000000000 )
b1000000000000 +
b1000 ,
b10000 (
b10000 /
b1000 0
b11 #
b11 &
b11 *
b11 .
b11 %
#400
b1000000010000000 !
b1000000010000000 '
b1000000000000000 )
b1000000000000000 +
b1000 ,
b10000000 (
b10000000 /
b1000 0
b100 #
b100 &
b100 *
b100 .
b100 %
#420
b100000001000000 !
b100000001000000 '
b100000000000000 )
b100000000000000 +
b1000 ,
b1000000 (
b1000000 /
b1000 0
b101 #
b101 &
b101 *
b101 .
b101 %
#440
b10000000100000 !
b10000000100000 '
b10000000000000 )
b10000000000000 +
b1000 ,
b100000 (
b100000 /
b1000 0
b110 #
b110 &
b110 *
b110 .
b110 %
#460
b1000000010000 !
b1000000010000 '
b1000000000000 )
b1000000000000 +
b1000 ,
b10000 (
b10000 /
b1000 0
b111 #
b111 &
b111 *
b111 .
b111 %
#480
b1000000010000000 !
b1000000010000000 '
b1000000000000000 )
b1000000000000000 +
b1000 ,
b10000000 (
b10000000 /
b1000 0
b1000 #
b1000 &
b1000 *
b1000 .
b1000 %
#500
b100000001000000 !
b100000001000000 '
b100000000000000 )
b100000000000000 +
b1000 ,
b1000000 (
b1000000 /
b1000 0
b1001 #
b1001 &
b1001 *
b1001 .
b1001 %
#520
b10000000100000 !
b10000000100000 '
b10000000000000 )
b10000000000000 +
b1000 ,
b100000 (
b100000 /
b1000 0
b1010 #
b1010 &
b1010 *
b1010 .
b1010 %
#540
b1000000010000 !
b1000000010000 '
b1000000000000 )
b1000000000000 +
b1000 ,
b10000 (
b10000 /
b1000 0
b1011 #
b1011 &
b1011 *
b1011 .
b1011 %
#560
b1000000010000000 !
b1000000010000000 '
b1000000000000000 )
b1000000000000000 +
b1000 ,
b10000000 (
b10000000 /
b1000 0
b1100 #
b1100 &
b1100 *
b1100 .
b1100 %
#580
b100000001000000 !
b100000001000000 '
b100000000000000 )
b100000000000000 +
b1000 ,
b1000000 (
b1000000 /
b1000 0
b1101 #
b1101 &
b1101 *
b1101 .
b1101 %
#600
b10000000100000 !
b10000000100000 '
b10000000000000 )
b10000000000000 +
b1000 ,
b100000 (
b100000 /
b1000 0
b1110 #
b1110 &
b1110 *
b1110 .
b1110 %
#620
b1000000010000 !
b1000000010000 '
b1000000000000 )
b1000000000000 +
b1000 ,
b10000 (
b10000 /
b1000 0
b1111 #
b1111 &
b1111 *
b1111 .
b1111 %
#640
b10 $
b10000 %
